{"caption":"","size":{"width":620,"height":640},"speed":30,"persist":false,"colour":"#00000000","enableviews":true,"showcolour":true,"clearbuf":false,"world":0,"bounding":{"top":0,"left":0,"bottom":768,"right":1024},"gravity":{"x":0.0,"y":10.0},"metresperpx":0.100000001490116,"drawbgcol":true,"bgs":[{"enabled":false,"foreground":false,"pos":{"x":0,"y":0},"tilex":true,"tiley":true,"speed":{"x":0,"y":0},"stretch":false},{"enabled":false,"foreground":false,"pos":{"x":0,"y":0},"tilex":true,"tiley":true,"speed":{"x":0,"y":0},"stretch":false},{"enabled":false,"foreground":false,"pos":{"x":0,"y":0},"tilex":true,"tiley":true,"speed":{"x":0,"y":0},"stretch":false},{"enabled":false,"foreground":false,"pos":{"x":0,"y":0},"tilex":true,"tiley":true,"speed":{"x":0,"y":0},"stretch":false},{"enabled":false,"foreground":false,"pos":{"x":0,"y":0},"tilex":true,"tiley":true,"speed":{"x":0,"y":0},"stretch":false},{"enabled":false,"foreground":false,"pos":{"x":0,"y":0},"tilex":true,"tiley":true,"speed":{"x":0,"y":0},"stretch":false},{"enabled":false,"foreground":false,"pos":{"x":0,"y":0},"tilex":true,"tiley":true,"speed":{"x":0,"y":0},"stretch":false},{"enabled":false,"foreground":false,"pos":{"x":0,"y":0},"tilex":true,"tiley":true,"speed":{"x":0,"y":0},"stretch":false}],"views":[{"enabled":true,"view":{"x":0,"y":0,"width":320,"height":240},"port":{"x":0,"y":0,"width":640,"height":480},"border":{"x":32,"y":32},"speed":{"x":-1,"y":-1},"obj":"obj_mainchara"},{"enabled":false,"view":{"x":0,"y":0,"width":640,"height":480},"port":{"x":0,"y":0,"width":640,"height":480},"border":{"x":32,"y":32},"speed":{"x":-1,"y":-1}},{"enabled":false,"view":{"x":0,"y":0,"width":640,"height":480},"port":{"x":0,"y":0,"width":640,"height":480},"border":{"x":32,"y":32},"speed":{"x":-1,"y":-1}},{"enabled":false,"view":{"x":0,"y":0,"width":640,"height":480},"port":{"x":0,"y":0,"width":640,"height":480},"border":{"x":32,"y":32},"speed":{"x":-1,"y":-1}},{"enabled":false,"view":{"x":0,"y":0,"width":640,"height":480},"port":{"x":0,"y":0,"width":640,"height":480},"border":{"x":32,"y":32},"speed":{"x":-1,"y":-1}},{"enabled":false,"view":{"x":0,"y":0,"width":640,"height":480},"port":{"x":0,"y":0,"width":640,"height":480},"border":{"x":32,"y":32},"speed":{"x":-1,"y":-1}},{"enabled":false,"view":{"x":0,"y":0,"width":640,"height":480},"port":{"x":0,"y":0,"width":640,"height":480},"border":{"x":32,"y":32},"speed":{"x":-1,"y":-1}},{"enabled":false,"view":{"x":0,"y":0,"width":640,"height":480},"port":{"x":0,"y":0,"width":640,"height":480},"border":{"x":32,"y":32},"speed":{"x":-1,"y":-1}}],"objs":[{"pos":{"x":200,"y":240},"obj":"obj_glowshroom","scale":{"x":1.0,"y":1.0},"colour":"#FFFFFFFF","rotation":0.0,"instanceid":106616,"createcodeid":4294967295},{"pos":{"x":200,"y":380},"obj":"obj_glowshroom","scale":{"x":1.0,"y":1.0},"colour":"#FFFFFFFF","rotation":0.0,"instanceid":106617,"createcodeid":4294967295},{"pos":{"x":340,"y":540},"obj":"obj_glowshroom","scale":{"x":1.0,"y":1.0},"colour":"#FFFFFFFF","rotation":0.0,"instanceid":106618,"createcodeid":4294967295},{"pos":{"x":340,"y":380},"obj":"obj_glowshroom","scale":{"x":1.0,"y":1.0},"colour":"#FFFFFFFF","rotation":0.0,"instanceid":106619,"createcodeid":4294967295},{"pos":{"x":140,"y":100},"obj":"obj_mainchara","scale":{"x":1.0,"y":1.0},"colour":"#FFFFFFFF","rotation":0.0,"instanceid":106620,"createcodeid":4294967295},{"pos":{"x":160,"y":140},"obj":"obj_solidsmall","scale":{"x":1.0,"y":1.0},"colour":"#FFFFFFFF","rotation":0.0,"instanceid":106621,"createcodeid":4294967295},{"pos":{"x":180,"y":140},"obj":"obj_solidthin","scale":{"x":1.0,"y":1.0},"colour":"#FFFFFFFF","rotation":0.0,"instanceid":106622,"createcodeid":4294967295},{"pos":{"x":180,"y":160},"obj":"obj_solidthin","scale":{"x":1.0,"y":1.0},"colour":"#FFFFFFFF","rotation":0.0,"instanceid":106623,"createcodeid":4294967295},{"pos":{"x":180,"y":180},"obj":"obj_solidthin","scale":{"x":1.0,"y":1.0},"colour":"#FFFFFFFF","rotation":0.0,"instanceid":106624,"createcodeid":4294967295},{"pos":{"x":180,"y":200},"obj":"obj_solidthin","scale":{"x":1.0,"y":1.0},"colour":"#FFFFFFFF","rotation":0.0,"instanceid":106625,"createcodeid":4294967295},{"pos":{"x":220,"y":100},"obj":"obj_solidthin","scale":{"x":1.0,"y":1.0},"colour":"#FFFFFFFF","rotation":0.0,"instanceid":106626,"createcodeid":4294967295},{"pos":{"x":220,"y":120},"obj":"obj_solidthin","scale":{"x":1.0,"y":1.0},"colour":"#FFFFFFFF","rotation":0.0,"instanceid":106627,"createcodeid":4294967295},{"pos":{"x":220,"y":140},"obj":"obj_solidthin","scale":{"x":1.0,"y":1.0},"colour":"#FFFFFFFF","rotation":0.0,"instanceid":106628,"createcodeid":4294967295},{"pos":{"x":220,"y":160},"obj":"obj_solidthin","scale":{"x":1.0,"y":1.0},"colour":"#FFFFFFFF","rotation":0.0,"instanceid":106629,"createcodeid":4294967295},{"pos":{"x":220,"y":180},"obj":"obj_solidthin","scale":{"x":1.0,"y":1.0},"colour":"#FFFFFFFF","rotation":0.0,"instanceid":106630,"createcodeid":4294967295},{"pos":{"x":220,"y":200},"obj":"obj_solidthin","scale":{"x":1.0,"y":1.0},"colour":"#FFFFFFFF","rotation":0.0,"instanceid":106631,"createcodeid":4294967295},{"pos":{"x":160,"y":220},"obj":"obj_solidthin","scale":{"x":1.0,"y":1.0},"colour":"#FFFFFFFF","rotation":0.0,"instanceid":106632,"createcodeid":4294967295},{"pos":{"x":160,"y":260},"obj":"obj_solidthin","scale":{"x":1.0,"y":1.0},"colour":"#FFFFFFFF","rotation":0.0,"instanceid":106633,"createcodeid":4294967295},{"pos":{"x":240,"y":260},"obj":"obj_solidthin","scale":{"x":1.0,"y":1.0},"colour":"#FFFFFFFF","rotation":0.0,"instanceid":106634,"createcodeid":4294967295},{"pos":{"x":240,"y":220},"obj":"obj_solidthin","scale":{"x":1.0,"y":1.0},"colour":"#FFFFFFFF","rotation":0.0,"instanceid":106635,"createcodeid":4294967295},{"pos":{"x":360,"y":240},"obj":"obj_solidthin","scale":{"x":1.0,"y":1.0},"colour":"#FFFFFFFF","rotation":0.0,"instanceid":106636,"createcodeid":4294967295},{"pos":{"x":360,"y":260},"obj":"obj_solidthin","scale":{"x":1.0,"y":1.0},"colour":"#FFFFFFFF","rotation":0.0,"instanceid":106637,"createcodeid":4294967295},{"pos":{"x":360,"y":280},"obj":"obj_solidthin","scale":{"x":1.0,"y":1.0},"colour":"#FFFFFFFF","rotation":0.0,"instanceid":106638,"createcodeid":4294967295},{"pos":{"x":360,"y":300},"obj":"obj_solidthin","scale":{"x":1.0,"y":1.0},"colour":"#FFFFFFFF","rotation":0.0,"instanceid":106639,"createcodeid":4294967295},{"pos":{"x":360,"y":320},"obj":"obj_solidthin","scale":{"x":1.0,"y":1.0},"colour":"#FFFFFFFF","rotation":0.0,"instanceid":106640,"createcodeid":4294967295},{"pos":{"x":360,"y":340},"obj":"obj_solidthin","scale":{"x":1.0,"y":1.0},"colour":"#FFFFFFFF","rotation":0.0,"instanceid":106641,"createcodeid":4294967295},{"pos":{"x":380,"y":360},"obj":"obj_solidthin","scale":{"x":1.0,"y":1.0},"colour":"#FFFFFFFF","rotation":0.0,"instanceid":106642,"createcodeid":4294967295},{"pos":{"x":380,"y":340},"obj":"obj_solidthin","scale":{"x":1.0,"y":1.0},"colour":"#FFFFFFFF","rotation":0.0,"instanceid":106643,"createcodeid":4294967295},{"pos":{"x":380,"y":320},"obj":"obj_solidthin","scale":{"x":1.0,"y":1.0},"colour":"#FFFFFFFF","rotation":0.0,"instanceid":106644,"createcodeid":4294967295},{"pos":{"x":380,"y":300},"obj":"obj_solidthin","scale":{"x":1.0,"y":1.0},"colour":"#FFFFFFFF","rotation":0.0,"instanceid":106645,"createcodeid":4294967295},{"pos":{"x":380,"y":280},"obj":"obj_solidthin","scale":{"x":1.0,"y":1.0},"colour":"#FFFFFFFF","rotation":0.0,"instanceid":106646,"createcodeid":4294967295},{"pos":{"x":380,"y":260},"obj":"obj_solidthin","scale":{"x":1.0,"y":1.0},"colour":"#FFFFFFFF","rotation":0.0,"instanceid":106647,"createcodeid":4294967295},{"pos":{"x":380,"y":240},"obj":"obj_solidthin","scale":{"x":1.0,"y":1.0},"colour":"#FFFFFFFF","rotation":0.0,"instanceid":106648,"createcodeid":4294967295},{"pos":{"x":460,"y":220},"obj":"obj_solidthin","scale":{"x":1.0,"y":1.0},"colour":"#FFFFFFFF","rotation":0.0,"instanceid":106649,"createcodeid":4294967295},{"pos":{"x":460,"y":200},"obj":"obj_solidthin","scale":{"x":1.0,"y":1.0},"colour":"#FFFFFFFF","rotation":0.0,"instanceid":106650,"createcodeid":4294967295},{"pos":{"x":460,"y":180},"obj":"obj_solidthin","scale":{"x":1.0,"y":1.0},"colour":"#FFFFFFFF","rotation":0.0,"instanceid":106651,"createcodeid":4294967295},{"pos":{"x":460,"y":160},"obj":"obj_solidthin","scale":{"x":1.0,"y":1.0},"colour":"#FFFFFFFF","rotation":0.0,"instanceid":106652,"createcodeid":4294967295},{"pos":{"x":460,"y":140},"obj":"obj_solidthin","scale":{"x":1.0,"y":1.0},"colour":"#FFFFFFFF","rotation":0.0,"instanceid":106653,"createcodeid":4294967295},{"pos":{"x":460,"y":120},"obj":"obj_solidthin","scale":{"x":1.0,"y":1.0},"colour":"#FFFFFFFF","rotation":0.0,"instanceid":106654,"createcodeid":4294967295},{"pos":{"x":500,"y":140},"obj":"obj_solidthin","scale":{"x":1.0,"y":1.0},"colour":"#FFFFFFFF","rotation":0.0,"instanceid":106655,"createcodeid":4294967295},{"pos":{"x":500,"y":160},"obj":"obj_solidthin","scale":{"x":1.0,"y":1.0},"colour":"#FFFFFFFF","rotation":0.0,"instanceid":106656,"createcodeid":4294967295},{"pos":{"x":500,"y":180},"obj":"obj_solidthin","scale":{"x":1.0,"y":1.0},"colour":"#FFFFFFFF","rotation":0.0,"instanceid":106657,"createcodeid":4294967295},{"pos":{"x":500,"y":200},"obj":"obj_solidthin","scale":{"x":1.0,"y":1.0},"colour":"#FFFFFFFF","rotation":0.0,"instanceid":106658,"createcodeid":4294967295},{"pos":{"x":500,"y":220},"obj":"obj_solidthin","scale":{"x":1.0,"y":1.0},"colour":"#FFFFFFFF","rotation":0.0,"instanceid":106659,"createcodeid":4294967295},{"pos":{"x":500,"y":240},"obj":"obj_solidthin","scale":{"x":1.0,"y":1.0},"colour":"#FFFFFFFF","rotation":0.0,"instanceid":106660,"createcodeid":4294967295},{"pos":{"x":520,"y":220},"obj":"obj_solidthin","scale":{"x":1.0,"y":1.0},"colour":"#FFFFFFFF","rotation":0.0,"instanceid":106661,"createcodeid":4294967295},{"pos":{"x":520,"y":200},"obj":"obj_solidthin","scale":{"x":1.0,"y":1.0},"colour":"#FFFFFFFF","rotation":0.0,"instanceid":106662,"createcodeid":4294967295},{"pos":{"x":520,"y":180},"obj":"obj_solidthin","scale":{"x":1.0,"y":1.0},"colour":"#FFFFFFFF","rotation":0.0,"instanceid":106663,"createcodeid":4294967295},{"pos":{"x":520,"y":160},"obj":"obj_solidthin","scale":{"x":1.0,"y":1.0},"colour":"#FFFFFFFF","rotation":0.0,"instanceid":106664,"createcodeid":4294967295},{"pos":{"x":520,"y":140},"obj":"obj_solidthin","scale":{"x":1.0,"y":1.0},"colour":"#FFFFFFFF","rotation":0.0,"instanceid":106665,"createcodeid":4294967295},{"pos":{"x":520,"y":240},"obj":"obj_solidthin","scale":{"x":1.0,"y":1.0},"colour":"#FFFFFFFF","rotation":0.0,"instanceid":106666,"createcodeid":4294967295},{"pos":{"x":560,"y":120},"obj":"obj_solidthin","scale":{"x":1.0,"y":1.0},"colour":"#FFFFFFFF","rotation":0.0,"instanceid":106667,"createcodeid":4294967295},{"pos":{"x":560,"y":140},"obj":"obj_solidthin","scale":{"x":1.0,"y":1.0},"colour":"#FFFFFFFF","rotation":0.0,"instanceid":106668,"createcodeid":4294967295},{"pos":{"x":560,"y":160},"obj":"obj_solidthin","scale":{"x":1.0,"y":1.0},"colour":"#FFFFFFFF","rotation":0.0,"instanceid":106669,"createcodeid":4294967295},{"pos":{"x":560,"y":180},"obj":"obj_solidthin","scale":{"x":1.0,"y":1.0},"colour":"#FFFFFFFF","rotation":0.0,"instanceid":106670,"createcodeid":4294967295},{"pos":{"x":560,"y":200},"obj":"obj_solidthin","scale":{"x":1.0,"y":1.0},"colour":"#FFFFFFFF","rotation":0.0,"instanceid":106671,"createcodeid":4294967295},{"pos":{"x":560,"y":220},"obj":"obj_solidthin","scale":{"x":1.0,"y":1.0},"colour":"#FFFFFFFF","rotation":0.0,"instanceid":106672,"createcodeid":4294967295},{"pos":{"x":420,"y":260},"obj":"obj_solidthin","scale":{"x":1.0,"y":1.0},"colour":"#FFFFFFFF","rotation":0.0,"instanceid":106673,"createcodeid":4294967295},{"pos":{"x":420,"y":280},"obj":"obj_solidthin","scale":{"x":1.0,"y":1.0},"colour":"#FFFFFFFF","rotation":0.0,"instanceid":106674,"createcodeid":4294967295},{"pos":{"x":420,"y":300},"obj":"obj_solidthin","scale":{"x":1.0,"y":1.0},"colour":"#FFFFFFFF","rotation":0.0,"instanceid":106675,"createcodeid":4294967295},{"pos":{"x":420,"y":320},"obj":"obj_solidthin","scale":{"x":1.0,"y":1.0},"colour":"#FFFFFFFF","rotation":0.0,"instanceid":106676,"createcodeid":4294967295},{"pos":{"x":420,"y":340},"obj":"obj_solidthin","scale":{"x":1.0,"y":1.0},"colour":"#FFFFFFFF","rotation":0.0,"instanceid":106677,"createcodeid":4294967295},{"pos":{"x":420,"y":360},"obj":"obj_solidthin","scale":{"x":1.0,"y":1.0},"colour":"#FFFFFFFF","rotation":0.0,"instanceid":106678,"createcodeid":4294967295},{"pos":{"x":420,"y":380},"obj":"obj_solidthin","scale":{"x":1.0,"y":1.0},"colour":"#FFFFFFFF","rotation":0.0,"instanceid":106679,"createcodeid":4294967295},{"pos":{"x":540,"y":380},"obj":"obj_solidthin","scale":{"x":1.0,"y":1.0},"colour":"#FFFFFFFF","rotation":0.0,"instanceid":106680,"createcodeid":4294967295},{"pos":{"x":540,"y":400},"obj":"obj_solidthin","scale":{"x":1.0,"y":1.0},"colour":"#FFFFFFFF","rotation":0.0,"instanceid":106681,"createcodeid":4294967295},{"pos":{"x":540,"y":420},"obj":"obj_solidthin","scale":{"x":1.0,"y":1.0},"colour":"#FFFFFFFF","rotation":0.0,"instanceid":106682,"createcodeid":4294967295},{"pos":{"x":540,"y":440},"obj":"obj_solidthin","scale":{"x":1.0,"y":1.0},"colour":"#FFFFFFFF","rotation":0.0,"instanceid":106683,"createcodeid":4294967295},{"pos":{"x":540,"y":460},"obj":"obj_solidthin","scale":{"x":1.0,"y":1.0},"colour":"#FFFFFFFF","rotation":0.0,"instanceid":106684,"createcodeid":4294967295},{"pos":{"x":540,"y":480},"obj":"obj_solidthin","scale":{"x":1.0,"y":1.0},"colour":"#FFFFFFFF","rotation":0.0,"instanceid":106685,"createcodeid":4294967295},{"pos":{"x":540,"y":500},"obj":"obj_solidthin","scale":{"x":1.0,"y":1.0},"colour":"#FFFFFFFF","rotation":0.0,"instanceid":106686,"createcodeid":4294967295},{"pos":{"x":540,"y":520},"obj":"obj_solidthin","scale":{"x":1.0,"y":1.0},"colour":"#FFFFFFFF","rotation":0.0,"instanceid":106687,"createcodeid":4294967295},{"pos":{"x":540,"y":540},"obj":"obj_solidthin","scale":{"x":1.0,"y":1.0},"colour":"#FFFFFFFF","rotation":0.0,"instanceid":106688,"createcodeid":4294967295},{"pos":{"x":540,"y":560},"obj":"obj_solidthin","scale":{"x":1.0,"y":1.0},"colour":"#FFFFFFFF","rotation":0.0,"instanceid":106689,"createcodeid":4294967295},{"pos":{"x":540,"y":580},"obj":"obj_solidthin","scale":{"x":1.0,"y":1.0},"colour":"#FFFFFFFF","rotation":0.0,"instanceid":106690,"createcodeid":4294967295},{"pos":{"x":540,"y":600},"obj":"obj_solidthin","scale":{"x":1.0,"y":1.0},"colour":"#FFFFFFFF","rotation":0.0,"instanceid":106691,"createcodeid":4294967295},{"pos":{"x":540,"y":620},"obj":"obj_solidthin","scale":{"x":1.0,"y":1.0},"colour":"#FFFFFFFF","rotation":0.0,"instanceid":106692,"createcodeid":4294967295},{"pos":{"x":540,"y":640},"obj":"obj_solidthin","scale":{"x":1.0,"y":1.0},"colour":"#FFFFFFFF","rotation":0.0,"instanceid":106693,"createcodeid":4294967295},{"pos":{"x":500,"y":560},"obj":"obj_solidthin","scale":{"x":1.0,"y":1.0},"colour":"#FFFFFFFF","rotation":0.0,"instanceid":106694,"createcodeid":4294967295},{"pos":{"x":500,"y":580},"obj":"obj_solidthin","scale":{"x":1.0,"y":1.0},"colour":"#FFFFFFFF","rotation":0.0,"instanceid":106695,"createcodeid":4294967295},{"pos":{"x":500,"y":600},"obj":"obj_solidthin","scale":{"x":1.0,"y":1.0},"colour":"#FFFFFFFF","rotation":0.0,"instanceid":106696,"createcodeid":4294967295},{"pos":{"x":500,"y":620},"obj":"obj_solidthin","scale":{"x":1.0,"y":1.0},"colour":"#FFFFFFFF","rotation":0.0,"instanceid":106697,"createcodeid":4294967295},{"pos":{"x":500,"y":520},"obj":"obj_solidthin","scale":{"x":1.0,"y":1.0},"colour":"#FFFFFFFF","rotation":0.0,"instanceid":106698,"createcodeid":4294967295},{"pos":{"x":500,"y":500},"obj":"obj_solidthin","scale":{"x":1.0,"y":1.0},"colour":"#FFFFFFFF","rotation":0.0,"instanceid":106699,"createcodeid":4294967295},{"pos":{"x":500,"y":480},"obj":"obj_solidthin","scale":{"x":1.0,"y":1.0},"colour":"#FFFFFFFF","rotation":0.0,"instanceid":106700,"createcodeid":4294967295},{"pos":{"x":500,"y":460},"obj":"obj_solidthin","scale":{"x":1.0,"y":1.0},"colour":"#FFFFFFFF","rotation":0.0,"instanceid":106701,"createcodeid":4294967295},{"pos":{"x":500,"y":440},"obj":"obj_solidthin","scale":{"x":1.0,"y":1.0},"colour":"#FFFFFFFF","rotation":0.0,"instanceid":106702,"createcodeid":4294967295},{"pos":{"x":500,"y":420},"obj":"obj_solidthin","scale":{"x":1.0,"y":1.0},"colour":"#FFFFFFFF","rotation":0.0,"instanceid":106703,"createcodeid":4294967295},{"pos":{"x":500,"y":400},"obj":"obj_solidthin","scale":{"x":1.0,"y":1.0},"colour":"#FFFFFFFF","rotation":0.0,"instanceid":106704,"createcodeid":4294967295},{"pos":{"x":380,"y":560},"obj":"obj_solidthin","scale":{"x":1.0,"y":1.0},"colour":"#FFFFFFFF","rotation":0.0,"instanceid":106705,"createcodeid":4294967295},{"pos":{"x":380,"y":520},"obj":"obj_solidthin","scale":{"x":1.0,"y":1.0},"colour":"#FFFFFFFF","rotation":0.0,"instanceid":106706,"createcodeid":4294967295},{"pos":{"x":300,"y":520},"obj":"obj_solidthin","scale":{"x":1.0,"y":1.0},"colour":"#FFFFFFFF","rotation":0.0,"instanceid":106707,"createcodeid":4294967295},{"pos":{"x":300,"y":560},"obj":"obj_solidthin","scale":{"x":1.0,"y":1.0},"colour":"#FFFFFFFF","rotation":0.0,"instanceid":106708,"createcodeid":4294967295},{"pos":{"x":220,"y":520},"obj":"obj_solidthin","scale":{"x":1.0,"y":1.0},"colour":"#FFFFFFFF","rotation":0.0,"instanceid":106709,"createcodeid":4294967295},{"pos":{"x":220,"y":500},"obj":"obj_solidthin","scale":{"x":1.0,"y":1.0},"colour":"#FFFFFFFF","rotation":0.0,"instanceid":106710,"createcodeid":4294967295},{"pos":{"x":220,"y":480},"obj":"obj_solidthin","scale":{"x":1.0,"y":1.0},"colour":"#FFFFFFFF","rotation":0.0,"instanceid":106711,"createcodeid":4294967295},{"pos":{"x":220,"y":460},"obj":"obj_solidthin","scale":{"x":1.0,"y":1.0},"colour":"#FFFFFFFF","rotation":0.0,"instanceid":106712,"createcodeid":4294967295},{"pos":{"x":220,"y":440},"obj":"obj_solidthin","scale":{"x":1.0,"y":1.0},"colour":"#FFFFFFFF","rotation":0.0,"instanceid":106713,"createcodeid":4294967295},{"pos":{"x":220,"y":420},"obj":"obj_solidthin","scale":{"x":1.0,"y":1.0},"colour":"#FFFFFFFF","rotation":0.0,"instanceid":106714,"createcodeid":4294967295},{"pos":{"x":180,"y":420},"obj":"obj_solidthin","scale":{"x":1.0,"y":1.0},"colour":"#FFFFFFFF","rotation":0.0,"instanceid":106715,"createcodeid":4294967295},{"pos":{"x":180,"y":440},"obj":"obj_solidthin","scale":{"x":1.0,"y":1.0},"colour":"#FFFFFFFF","rotation":0.0,"instanceid":106716,"createcodeid":4294967295},{"pos":{"x":180,"y":460},"obj":"obj_solidthin","scale":{"x":1.0,"y":1.0},"colour":"#FFFFFFFF","rotation":0.0,"instanceid":106717,"createcodeid":4294967295},{"pos":{"x":180,"y":480},"obj":"obj_solidthin","scale":{"x":1.0,"y":1.0},"colour":"#FFFFFFFF","rotation":0.0,"instanceid":106718,"createcodeid":4294967295},{"pos":{"x":180,"y":500},"obj":"obj_solidthin","scale":{"x":1.0,"y":1.0},"colour":"#FFFFFFFF","rotation":0.0,"instanceid":106719,"createcodeid":4294967295},{"pos":{"x":180,"y":520},"obj":"obj_solidthin","scale":{"x":1.0,"y":1.0},"colour":"#FFFFFFFF","rotation":0.0,"instanceid":106720,"createcodeid":4294967295},{"pos":{"x":180,"y":540},"obj":"obj_solidthin","scale":{"x":1.0,"y":1.0},"colour":"#FFFFFFFF","rotation":0.0,"instanceid":106721,"createcodeid":4294967295},{"pos":{"x":240,"y":400},"obj":"obj_solidthin","scale":{"x":1.0,"y":1.0},"colour":"#FFFFFFFF","rotation":0.0,"instanceid":106722,"createcodeid":4294967295},{"pos":{"x":240,"y":380},"obj":"obj_solidthin","scale":{"x":1.0,"y":1.0},"colour":"#FFFFFFFF","rotation":0.0,"instanceid":106723,"createcodeid":4294967295},{"pos":{"x":240,"y":360},"obj":"obj_solidthin","scale":{"x":1.0,"y":1.0},"colour":"#FFFFFFFF","rotation":0.0,"instanceid":106724,"createcodeid":4294967295},{"pos":{"x":160,"y":360},"obj":"obj_solidthin","scale":{"x":1.0,"y":1.0},"colour":"#FFFFFFFF","rotation":0.0,"instanceid":106725,"createcodeid":4294967295},{"pos":{"x":160,"y":400},"obj":"obj_solidthin","scale":{"x":1.0,"y":1.0},"colour":"#FFFFFFFF","rotation":0.0,"instanceid":106726,"createcodeid":4294967295},{"pos":{"x":80,"y":360},"obj":"obj_solidthin","scale":{"x":1.0,"y":1.0},"colour":"#FFFFFFFF","rotation":0.0,"instanceid":106727,"createcodeid":4294967295},{"pos":{"x":80,"y":340},"obj":"obj_solidthin","scale":{"x":1.0,"y":1.0},"colour":"#FFFFFFFF","rotation":0.0,"instanceid":106728,"createcodeid":4294967295},{"pos":{"x":80,"y":320},"obj":"obj_solidthin","scale":{"x":1.0,"y":1.0},"colour":"#FFFFFFFF","rotation":0.0,"instanceid":106729,"createcodeid":4294967295},{"pos":{"x":80,"y":300},"obj":"obj_solidthin","scale":{"x":1.0,"y":1.0},"colour":"#FFFFFFFF","rotation":0.0,"instanceid":106730,"createcodeid":4294967295},{"pos":{"x":80,"y":280},"obj":"obj_solidthin","scale":{"x":1.0,"y":1.0},"colour":"#FFFFFFFF","rotation":0.0,"instanceid":106731,"createcodeid":4294967295},{"pos":{"x":80,"y":260},"obj":"obj_solidthin","scale":{"x":1.0,"y":1.0},"colour":"#FFFFFFFF","rotation":0.0,"instanceid":106732,"createcodeid":4294967295},{"pos":{"x":40,"y":240},"obj":"obj_solidthin","scale":{"x":1.0,"y":1.0},"colour":"#FFFFFFFF","rotation":0.0,"instanceid":106733,"createcodeid":4294967295},{"pos":{"x":40,"y":260},"obj":"obj_solidthin","scale":{"x":1.0,"y":1.0},"colour":"#FFFFFFFF","rotation":0.0,"instanceid":106734,"createcodeid":4294967295},{"pos":{"x":40,"y":280},"obj":"obj_solidthin","scale":{"x":1.0,"y":1.0},"colour":"#FFFFFFFF","rotation":0.0,"instanceid":106735,"createcodeid":4294967295},{"pos":{"x":40,"y":300},"obj":"obj_solidthin","scale":{"x":1.0,"y":1.0},"colour":"#FFFFFFFF","rotation":0.0,"instanceid":106736,"createcodeid":4294967295},{"pos":{"x":40,"y":320},"obj":"obj_solidthin","scale":{"x":1.0,"y":1.0},"colour":"#FFFFFFFF","rotation":0.0,"instanceid":106737,"createcodeid":4294967295},{"pos":{"x":40,"y":340},"obj":"obj_solidthin","scale":{"x":1.0,"y":1.0},"colour":"#FFFFFFFF","rotation":0.0,"instanceid":106738,"createcodeid":4294967295},{"pos":{"x":40,"y":360},"obj":"obj_solidthin","scale":{"x":1.0,"y":1.0},"colour":"#FFFFFFFF","rotation":0.0,"instanceid":106739,"createcodeid":4294967295},{"pos":{"x":40,"y":380},"obj":"obj_solidthin","scale":{"x":1.0,"y":1.0},"colour":"#FFFFFFFF","rotation":0.0,"instanceid":106740,"createcodeid":4294967295},{"pos":{"x":320,"y":260},"obj":"obj_solidthin","scale":{"x":1.0,"y":1.0},"colour":"#FFFFFFFF","rotation":0.0,"instanceid":106741,"createcodeid":4294967295},{"pos":{"x":320,"y":280},"obj":"obj_solidthin","scale":{"x":1.0,"y":1.0},"colour":"#FFFFFFFF","rotation":0.0,"instanceid":106742,"createcodeid":4294967295},{"pos":{"x":320,"y":300},"obj":"obj_solidthin","scale":{"x":1.0,"y":1.0},"colour":"#FFFFFFFF","rotation":0.0,"instanceid":106743,"createcodeid":4294967295},{"pos":{"x":320,"y":320},"obj":"obj_solidthin","scale":{"x":1.0,"y":1.0},"colour":"#FFFFFFFF","rotation":0.0,"instanceid":106744,"createcodeid":4294967295},{"pos":{"x":320,"y":340},"obj":"obj_solidthin","scale":{"x":1.0,"y":1.0},"colour":"#FFFFFFFF","rotation":0.0,"instanceid":106745,"createcodeid":4294967295},{"pos":{"x":300,"y":360},"obj":"obj_solidthin","scale":{"x":1.0,"y":1.0},"colour":"#FFFFFFFF","rotation":0.0,"instanceid":106746,"createcodeid":4294967295},{"pos":{"x":300,"y":380},"obj":"obj_solidthin","scale":{"x":1.0,"y":1.0},"colour":"#FFFFFFFF","rotation":0.0,"instanceid":106747,"createcodeid":4294967295},{"pos":{"x":300,"y":400},"obj":"obj_solidthin","scale":{"x":1.0,"y":1.0},"colour":"#FFFFFFFF","rotation":0.0,"instanceid":106748,"createcodeid":4294967295},{"pos":{"x":380,"y":400},"obj":"obj_solidthin","scale":{"x":1.0,"y":1.0},"colour":"#FFFFFFFF","rotation":0.0,"instanceid":106749,"createcodeid":4294967295},{"pos":{"x":400,"y":400},"obj":"obj_solidsmall","scale":{"x":1.0,"y":1.0},"colour":"#FFFFFFFF","rotation":0.0,"instanceid":106750,"createcodeid":4294967295},{"pos":{"x":440,"y":380},"obj":"obj_solidsmall","scale":{"x":1.0,"y":1.0},"colour":"#FFFFFFFF","rotation":0.0,"instanceid":106751,"createcodeid":4294967295},{"pos":{"x":480,"y":520},"obj":"obj_solidsmall","scale":{"x":1.0,"y":1.0},"colour":"#FFFFFFFF","rotation":0.0,"instanceid":106752,"createcodeid":4294967295},{"pos":{"x":480,"y":560},"obj":"obj_solidsmall","scale":{"x":1.0,"y":1.0},"colour":"#FFFFFFFF","rotation":0.0,"instanceid":106753,"createcodeid":4294967295},{"pos":{"x":280,"y":560},"obj":"obj_solidsmall","scale":{"x":1.0,"y":1.0},"colour":"#FFFFFFFF","rotation":0.0,"instanceid":106754,"createcodeid":4294967295},{"pos":{"x":140,"y":400},"obj":"obj_solidsmall","scale":{"x":1.0,"y":1.0},"colour":"#FFFFFFFF","rotation":0.0,"instanceid":106755,"createcodeid":4294967295},{"pos":{"x":140,"y":220},"obj":"obj_solidsmall","scale":{"x":1.0,"y":1.0},"colour":"#FFFFFFFF","rotation":0.0,"instanceid":106756,"createcodeid":4294967295},{"pos":{"x":340,"y":220},"obj":"obj_solidsmall","scale":{"x":1.0,"y":1.0},"colour":"#FFFFFFFF","rotation":0.0,"instanceid":106757,"createcodeid":4294967295},{"pos":{"x":0,"y":100},"obj":"obj_doorB","scale":{"x":1.0,"y":1.0},"colour":"#FFFFFFFF","rotation":0.0,"instanceid":106758,"createcodeid":4294967295},{"pos":{"x":0,"y":120},"obj":"obj_doorB","scale":{"x":1.0,"y":1.0},"colour":"#FFFFFFFF","rotation":0.0,"instanceid":106759,"createcodeid":4294967295},{"pos":{"x":20,"y":100},"obj":"obj_markerA","scale":{"x":1.0,"y":1.0},"colour":"#FFFFFFFF","rotation":0.0,"instanceid":106760,"createcodeid":4294967295},{"pos":{"x":140,"y":360},"obj":"obj_solidsmall","scale":{"x":1.0,"y":1.0},"colour":"#FFFFFFFF","rotation":0.0,"instanceid":106761,"createcodeid":4294967295},{"pos":{"x":140,"y":260},"obj":"obj_solidsmall","scale":{"x":1.0,"y":1.0},"colour":"#FFFFFFFF","rotation":0.0,"instanceid":106762,"createcodeid":4294967295},{"pos":{"x":220,"y":340},"obj":"obj_solidsmall","scale":{"x":1.0,"y":1.0},"colour":"#FFFFFFFF","rotation":0.0,"instanceid":106763,"createcodeid":4294967295},{"pos":{"x":300,"y":260},"obj":"obj_solidsmall","scale":{"x":1.0,"y":1.0},"colour":"#FFFFFFFF","rotation":0.0,"instanceid":106764,"createcodeid":4294967295},{"pos":{"x":280,"y":520},"obj":"obj_solidsmall","scale":{"x":1.0,"y":1.0},"colour":"#FFFFFFFF","rotation":0.0,"instanceid":106765,"createcodeid":4294967295},{"pos":{"x":360,"y":500},"obj":"obj_solidsmall","scale":{"x":1.0,"y":1.0},"colour":"#FFFFFFFF","rotation":0.0,"instanceid":106766,"createcodeid":4294967295},{"pos":{"x":360,"y":580},"obj":"obj_solidsmall","scale":{"x":1.0,"y":1.0},"colour":"#FFFFFFFF","rotation":0.0,"instanceid":106767,"createcodeid":4294967295},{"pos":{"x":460,"y":400},"obj":"obj_solidsmall","scale":{"x":1.0,"y":1.0},"colour":"#FFFFFFFF","rotation":0.0,"instanceid":106768,"createcodeid":4294967295},{"pos":{"x":480,"y":400},"obj":"obj_solidsmall","scale":{"x":1.0,"y":1.0},"colour":"#FFFFFFFF","rotation":0.0,"instanceid":106769,"createcodeid":4294967295},{"pos":{"x":360,"y":420},"obj":"obj_solidsmall","scale":{"x":1.0,"y":1.0},"colour":"#FFFFFFFF","rotation":0.0,"instanceid":106770,"createcodeid":4294967295},{"pos":{"x":80,"y":20},"obj":"obj_glowshroompuzzle","scale":{"x":1.0,"y":1.0},"colour":"#FFFFFFFF","rotation":0.0,"instanceid":106771,"createcodeid":4294967295},{"pos":{"x":600,"y":240},"obj":"obj_doorC","scale":{"x":1.0,"y":1.0},"colour":"#FFFFFFFF","rotation":0.0,"instanceid":106772,"createcodeid":4294967295},{"pos":{"x":580,"y":230},"obj":"obj_markerD","scale":{"x":1.0,"y":1.0},"colour":"#FFFFFFFF","rotation":0.0,"instanceid":106773,"createcodeid":4294967295},{"pos":{"x":100,"y":20},"obj":"obj_encounterer_water2","scale":{"x":1.0,"y":1.0},"colour":"#FFFFFFFF","rotation":0.0,"instanceid":106774,"createcodeid":4294967295},{"pos":{"x":520,"y":635},"obj":"obj_doorAmusicfade","scale":{"x":1.0,"y":1.0},"colour":"#FFFFFFFF","rotation":0.0,"instanceid":106775,"createcodeid":4294967295},{"pos":{"x":520,"y":600},"obj":"obj_markerB","scale":{"x":1.0,"y":1.0},"colour":"#FFFFFFFF","rotation":0.0,"instanceid":106776,"createcodeid":4294967295},{"pos":{"x":0,"y":140},"obj":"obj_solidexwide","scale":{"x":1.0,"y":1.0},"colour":"#FFFFFFFF","rotation":0.0,"instanceid":106777,"createcodeid":4294967295},{"pos":{"x":80,"y":140},"obj":"obj_solidexwide","scale":{"x":1.0,"y":1.0},"colour":"#FFFFFFFF","rotation":0.0,"instanceid":106778,"createcodeid":4294967295},{"pos":{"x":0,"y":80},"obj":"obj_solidexwide","scale":{"x":1.0,"y":1.0},"colour":"#FFFFFFFF","rotation":0.0,"instanceid":106779,"createcodeid":4294967295},{"pos":{"x":80,"y":80},"obj":"obj_solidexwide","scale":{"x":1.0,"y":1.0},"colour":"#FFFFFFFF","rotation":0.0,"instanceid":106780,"createcodeid":4294967295},{"pos":{"x":160,"y":80},"obj":"obj_solidexwide","scale":{"x":1.0,"y":1.0},"colour":"#FFFFFFFF","rotation":0.0,"instanceid":106781,"createcodeid":4294967295},{"pos":{"x":60,"y":400},"obj":"obj_solidexwide","scale":{"x":1.0,"y":1.0},"colour":"#FFFFFFFF","rotation":0.0,"instanceid":106782,"createcodeid":4294967295},{"pos":{"x":60,"y":220},"obj":"obj_solidexwide","scale":{"x":1.0,"y":1.0},"colour":"#FFFFFFFF","rotation":0.0,"instanceid":106783,"createcodeid":4294967295},{"pos":{"x":260,"y":220},"obj":"obj_solidexwide","scale":{"x":1.0,"y":1.0},"colour":"#FFFFFFFF","rotation":0.0,"instanceid":106784,"createcodeid":4294967295},{"pos":{"x":380,"y":220},"obj":"obj_solidexwide","scale":{"x":1.0,"y":1.0},"colour":"#FFFFFFFF","rotation":0.0,"instanceid":106785,"createcodeid":4294967295},{"pos":{"x":440,"y":260},"obj":"obj_solidexwide","scale":{"x":1.0,"y":1.0},"colour":"#FFFFFFFF","rotation":0.0,"instanceid":106786,"createcodeid":4294967295},{"pos":{"x":480,"y":100},"obj":"obj_solidexwide","scale":{"x":1.0,"y":1.0},"colour":"#FFFFFFFF","rotation":0.0,"instanceid":106787,"createcodeid":4294967295},{"pos":{"x":540,"y":260},"obj":"obj_solidexwide","scale":{"x":1.0,"y":1.0},"colour":"#FFFFFFFF","rotation":0.0,"instanceid":106788,"createcodeid":4294967295},{"pos":{"x":160,"y":280},"obj":"obj_solidexwide","scale":{"x":1.0,"y":1.0},"colour":"#FFFFFFFF","rotation":0.0,"instanceid":106789,"createcodeid":4294967295},{"pos":{"x":400,"y":520},"obj":"obj_solidexwide","scale":{"x":1.0,"y":1.0},"colour":"#FFFFFFFF","rotation":0.0,"instanceid":106790,"createcodeid":4294967295},{"pos":{"x":400,"y":560},"obj":"obj_solidexwide","scale":{"x":1.0,"y":1.0},"colour":"#FFFFFFFF","rotation":0.0,"instanceid":106791,"createcodeid":4294967295},{"pos":{"x":200,"y":560},"obj":"obj_solidexwide","scale":{"x":1.0,"y":1.0},"colour":"#FFFFFFFF","rotation":0.0,"instanceid":106792,"createcodeid":4294967295},{"pos":{"x":460,"y":360},"obj":"obj_solidexwide","scale":{"x":1.0,"y":1.0},"colour":"#FFFFFFFF","rotation":0.0,"instanceid":106793,"createcodeid":4294967295},{"pos":{"x":100,"y":260},"obj":"obj_solidwide","scale":{"x":1.0,"y":1.0},"colour":"#FFFFFFFF","rotation":0.0,"instanceid":106794,"createcodeid":4294967295},{"pos":{"x":100,"y":360},"obj":"obj_solidwide","scale":{"x":1.0,"y":1.0},"colour":"#FFFFFFFF","rotation":0.0,"instanceid":106795,"createcodeid":4294967295},{"pos":{"x":260,"y":260},"obj":"obj_solidwide","scale":{"x":1.0,"y":1.0},"colour":"#FFFFFFFF","rotation":0.0,"instanceid":106796,"createcodeid":4294967295},{"pos":{"x":180,"y":340},"obj":"obj_solidwide","scale":{"x":1.0,"y":1.0},"colour":"#FFFFFFFF","rotation":0.0,"instanceid":106797,"createcodeid":4294967295},{"pos":{"x":240,"y":520},"obj":"obj_solidwide","scale":{"x":1.0,"y":1.0},"colour":"#FFFFFFFF","rotation":0.0,"instanceid":106798,"createcodeid":4294967295},{"pos":{"x":320,"y":500},"obj":"obj_solidwide","scale":{"x":1.0,"y":1.0},"colour":"#FFFFFFFF","rotation":0.0,"instanceid":106799,"createcodeid":4294967295},{"pos":{"x":320,"y":580},"obj":"obj_solidwide","scale":{"x":1.0,"y":1.0},"colour":"#FFFFFFFF","rotation":0.0,"instanceid":106800,"createcodeid":4294967295},{"pos":{"x":320,"y":420},"obj":"obj_solidwide","scale":{"x":1.0,"y":1.0},"colour":"#FFFFFFFF","rotation":0.0,"instanceid":106801,"createcodeid":4294967295},{"pos":{"x":580,"y":220},"obj":"obj_solidwide","scale":{"x":1.0,"y":1.0},"colour":"#FFFFFFFF","rotation":0.0,"instanceid":106802,"createcodeid":4294967295},{"pos":{"x":20,"y":20},"obj":"obj_overworldcontroller","scale":{"x":1.0,"y":1.0},"colour":"#FFFFFFFF","rotation":0.0,"instanceid":106803,"createcodeid":4294967295},{"pos":{"x":130,"y":20},"obj":"obj_watermusic","scale":{"x":1.0,"y":1.0},"colour":"#FFFFFFFF","rotation":0.0,"instanceid":106804,"createcodeid":4294967295}],"tiles":[{"pos":{"x":520,"y":560},"bg":"bg_watertiles","sourcepos":{"x":80,"y":220},"size":{"width":20,"height":20},"scale":{"x":1.0,"y":1.0},"colour":"#FFFFFFFF","tiledepth":1000004,"instanceid":10037988},{"pos":{"x":520,"y":580},"bg":"bg_watertiles","sourcepos":{"x":80,"y":220},"size":{"width":20,"height":20},"scale":{"x":1.0,"y":1.0},"colour":"#FFFFFFFF","tiledepth":1000004,"instanceid":10037989},{"pos":{"x":520,"y":600},"bg":"bg_watertiles","sourcepos":{"x":80,"y":220},"size":{"width":20,"height":20},"scale":{"x":1.0,"y":1.0},"colour":"#FFFFFFFF","tiledepth":1000004,"instanceid":10037990},{"pos":{"x":520,"y":620},"bg":"bg_watertiles","sourcepos":{"x":80,"y":220},"size":{"width":20,"height":20},"scale":{"x":1.0,"y":1.0},"colour":"#FFFFFFFF","tiledepth":1000004,"instanceid":10037991},{"pos":{"x":400,"y":240},"bg":"bg_watertiles","sourcepos":{"x":80,"y":220},"size":{"width":20,"height":20},"scale":{"x":1.0,"y":1.0},"colour":"#FFFFFFFF","tiledepth":1000004,"instanceid":10037992},{"pos":{"x":420,"y":240},"bg":"bg_watertiles","sourcepos":{"x":80,"y":220},"size":{"width":20,"height":20},"scale":{"x":1.0,"y":1.0},"colour":"#FFFFFFFF","tiledepth":1000004,"instanceid":10037993},{"pos":{"x":440,"y":240},"bg":"bg_watertiles","sourcepos":{"x":80,"y":220},"size":{"width":20,"height":20},"scale":{"x":1.0,"y":1.0},"colour":"#FFFFFFFF","tiledepth":1000004,"instanceid":10037994},{"pos":{"x":460,"y":240},"bg":"bg_watertiles","sourcepos":{"x":80,"y":220},"size":{"width":20,"height":20},"scale":{"x":1.0,"y":1.0},"colour":"#FFFFFFFF","tiledepth":1000004,"instanceid":10037995},{"pos":{"x":480,"y":240},"bg":"bg_watertiles","sourcepos":{"x":80,"y":220},"size":{"width":20,"height":20},"scale":{"x":1.0,"y":1.0},"colour":"#FFFFFFFF","tiledepth":1000004,"instanceid":10037996},{"pos":{"x":480,"y":220},"bg":"bg_watertiles","sourcepos":{"x":80,"y":220},"size":{"width":20,"height":20},"scale":{"x":1.0,"y":1.0},"colour":"#FFFFFFFF","tiledepth":1000004,"instanceid":10037997},{"pos":{"x":480,"y":200},"bg":"bg_watertiles","sourcepos":{"x":80,"y":220},"size":{"width":20,"height":20},"scale":{"x":1.0,"y":1.0},"colour":"#FFFFFFFF","tiledepth":1000004,"instanceid":10037998},{"pos":{"x":480,"y":180},"bg":"bg_watertiles","sourcepos":{"x":80,"y":220},"size":{"width":20,"height":20},"scale":{"x":1.0,"y":1.0},"colour":"#FFFFFFFF","tiledepth":1000004,"instanceid":10037999},{"pos":{"x":480,"y":160},"bg":"bg_watertiles","sourcepos":{"x":80,"y":220},"size":{"width":20,"height":20},"scale":{"x":1.0,"y":1.0},"colour":"#FFFFFFFF","tiledepth":1000004,"instanceid":10038000},{"pos":{"x":480,"y":140},"bg":"bg_watertiles","sourcepos":{"x":80,"y":220},"size":{"width":20,"height":20},"scale":{"x":1.0,"y":1.0},"colour":"#FFFFFFFF","tiledepth":1000004,"instanceid":10038001},{"pos":{"x":480,"y":120},"bg":"bg_watertiles","sourcepos":{"x":80,"y":220},"size":{"width":20,"height":20},"scale":{"x":1.0,"y":1.0},"colour":"#FFFFFFFF","tiledepth":1000004,"instanceid":10038002},{"pos":{"x":500,"y":120},"bg":"bg_watertiles","sourcepos":{"x":80,"y":220},"size":{"width":20,"height":20},"scale":{"x":1.0,"y":1.0},"colour":"#FFFFFFFF","tiledepth":1000004,"instanceid":10038003},{"pos":{"x":520,"y":120},"bg":"bg_watertiles","sourcepos":{"x":80,"y":220},"size":{"width":20,"height":20},"scale":{"x":1.0,"y":1.0},"colour":"#FFFFFFFF","tiledepth":1000004,"instanceid":10038004},{"pos":{"x":540,"y":120},"bg":"bg_watertiles","sourcepos":{"x":80,"y":220},"size":{"width":20,"height":20},"scale":{"x":1.0,"y":1.0},"colour":"#FFFFFFFF","tiledepth":1000004,"instanceid":10038005},{"pos":{"x":540,"y":140},"bg":"bg_watertiles","sourcepos":{"x":80,"y":220},"size":{"width":20,"height":20},"scale":{"x":1.0,"y":1.0},"colour":"#FFFFFFFF","tiledepth":1000004,"instanceid":10038006},{"pos":{"x":540,"y":160},"bg":"bg_watertiles","sourcepos":{"x":80,"y":220},"size":{"width":20,"height":20},"scale":{"x":1.0,"y":1.0},"colour":"#FFFFFFFF","tiledepth":1000004,"instanceid":10038007},{"pos":{"x":540,"y":180},"bg":"bg_watertiles","sourcepos":{"x":80,"y":220},"size":{"width":20,"height":20},"scale":{"x":1.0,"y":1.0},"colour":"#FFFFFFFF","tiledepth":1000004,"instanceid":10038008},{"pos":{"x":540,"y":200},"bg":"bg_watertiles","sourcepos":{"x":80,"y":220},"size":{"width":20,"height":20},"scale":{"x":1.0,"y":1.0},"colour":"#FFFFFFFF","tiledepth":1000004,"instanceid":10038009},{"pos":{"x":540,"y":220},"bg":"bg_watertiles","sourcepos":{"x":80,"y":220},"size":{"width":20,"height":20},"scale":{"x":1.0,"y":1.0},"colour":"#FFFFFFFF","tiledepth":1000004,"instanceid":10038010},{"pos":{"x":540,"y":240},"bg":"bg_watertiles","sourcepos":{"x":80,"y":220},"size":{"width":20,"height":20},"scale":{"x":1.0,"y":1.0},"colour":"#FFFFFFFF","tiledepth":1000004,"instanceid":10038011},{"pos":{"x":560,"y":240},"bg":"bg_watertiles","sourcepos":{"x":80,"y":220},"size":{"width":20,"height":20},"scale":{"x":1.0,"y":1.0},"colour":"#FFFFFFFF","tiledepth":1000004,"instanceid":10038012},{"pos":{"x":580,"y":240},"bg":"bg_watertiles","sourcepos":{"x":80,"y":220},"size":{"width":20,"height":20},"scale":{"x":1.0,"y":1.0},"colour":"#FFFFFFFF","tiledepth":1000004,"instanceid":10038013},{"pos":{"x":600,"y":240},"bg":"bg_watertiles","sourcepos":{"x":80,"y":220},"size":{"width":20,"height":20},"scale":{"x":1.0,"y":1.0},"colour":"#FFFFFFFF","tiledepth":1000004,"instanceid":10038014},{"pos":{"x":400,"y":260},"bg":"bg_watertiles","sourcepos":{"x":80,"y":220},"size":{"width":20,"height":20},"scale":{"x":1.0,"y":1.0},"colour":"#FFFFFFFF","tiledepth":1000004,"instanceid":10038015},{"pos":{"x":400,"y":280},"bg":"bg_watertiles","sourcepos":{"x":80,"y":220},"size":{"width":20,"height":20},"scale":{"x":1.0,"y":1.0},"colour":"#FFFFFFFF","tiledepth":1000004,"instanceid":10038016},{"pos":{"x":400,"y":300},"bg":"bg_watertiles","sourcepos":{"x":80,"y":220},"size":{"width":20,"height":20},"scale":{"x":1.0,"y":1.0},"colour":"#FFFFFFFF","tiledepth":1000004,"instanceid":10038017},{"pos":{"x":400,"y":320},"bg":"bg_watertiles","sourcepos":{"x":80,"y":220},"size":{"width":20,"height":20},"scale":{"x":1.0,"y":1.0},"colour":"#FFFFFFFF","tiledepth":1000004,"instanceid":10038018},{"pos":{"x":400,"y":340},"bg":"bg_watertiles","sourcepos":{"x":80,"y":220},"size":{"width":20,"height":20},"scale":{"x":1.0,"y":1.0},"colour":"#FFFFFFFF","tiledepth":1000004,"instanceid":10038019},{"pos":{"x":400,"y":360},"bg":"bg_watertiles","sourcepos":{"x":80,"y":220},"size":{"width":20,"height":20},"scale":{"x":1.0,"y":1.0},"colour":"#FFFFFFFF","tiledepth":1000004,"instanceid":10038020},{"pos":{"x":400,"y":380},"bg":"bg_watertiles","sourcepos":{"x":80,"y":220},"size":{"width":20,"height":20},"scale":{"x":1.0,"y":1.0},"colour":"#FFFFFFFF","tiledepth":1000004,"instanceid":10038021},{"pos":{"x":380,"y":380},"bg":"bg_watertiles","sourcepos":{"x":80,"y":220},"size":{"width":20,"height":20},"scale":{"x":1.0,"y":1.0},"colour":"#FFFFFFFF","tiledepth":1000004,"instanceid":10038022},{"pos":{"x":360,"y":540},"bg":"bg_watertiles","sourcepos":{"x":80,"y":220},"size":{"width":20,"height":20},"scale":{"x":1.0,"y":1.0},"colour":"#FFFFFFFF","tiledepth":1000003,"instanceid":10038023},{"pos":{"x":380,"y":540},"bg":"bg_watertiles","sourcepos":{"x":80,"y":220},"size":{"width":20,"height":20},"scale":{"x":1.0,"y":1.0},"colour":"#FFFFFFFF","tiledepth":1000003,"instanceid":10038024},{"pos":{"x":400,"y":540},"bg":"bg_watertiles","sourcepos":{"x":80,"y":220},"size":{"width":20,"height":20},"scale":{"x":1.0,"y":1.0},"colour":"#FFFFFFFF","tiledepth":1000003,"instanceid":10038025},{"pos":{"x":420,"y":540},"bg":"bg_watertiles","sourcepos":{"x":80,"y":220},"size":{"width":20,"height":20},"scale":{"x":1.0,"y":1.0},"colour":"#FFFFFFFF","tiledepth":1000003,"instanceid":10038026},{"pos":{"x":440,"y":540},"bg":"bg_watertiles","sourcepos":{"x":80,"y":220},"size":{"width":20,"height":20},"scale":{"x":1.0,"y":1.0},"colour":"#FFFFFFFF","tiledepth":1000003,"instanceid":10038027},{"pos":{"x":460,"y":540},"bg":"bg_watertiles","sourcepos":{"x":80,"y":220},"size":{"width":20,"height":20},"scale":{"x":1.0,"y":1.0},"colour":"#FFFFFFFF","tiledepth":1000003,"instanceid":10038028},{"pos":{"x":480,"y":540},"bg":"bg_watertiles","sourcepos":{"x":80,"y":220},"size":{"width":20,"height":20},"scale":{"x":1.0,"y":1.0},"colour":"#FFFFFFFF","tiledepth":1000003,"instanceid":10038029},{"pos":{"x":500,"y":540},"bg":"bg_watertiles","sourcepos":{"x":80,"y":220},"size":{"width":20,"height":20},"scale":{"x":1.0,"y":1.0},"colour":"#FFFFFFFF","tiledepth":1000003,"instanceid":10038030},{"pos":{"x":520,"y":540},"bg":"bg_watertiles","sourcepos":{"x":80,"y":220},"size":{"width":20,"height":20},"scale":{"x":1.0,"y":1.0},"colour":"#FFFFFFFF","tiledepth":1000003,"instanceid":10038031},{"pos":{"x":520,"y":520},"bg":"bg_watertiles","sourcepos":{"x":80,"y":220},"size":{"width":20,"height":20},"scale":{"x":1.0,"y":1.0},"colour":"#FFFFFFFF","tiledepth":1000003,"instanceid":10038032},{"pos":{"x":520,"y":500},"bg":"bg_watertiles","sourcepos":{"x":80,"y":220},"size":{"width":20,"height":20},"scale":{"x":1.0,"y":1.0},"colour":"#FFFFFFFF","tiledepth":1000003,"instanceid":10038033},{"pos":{"x":520,"y":480},"bg":"bg_watertiles","sourcepos":{"x":80,"y":220},"size":{"width":20,"height":20},"scale":{"x":1.0,"y":1.0},"colour":"#FFFFFFFF","tiledepth":1000003,"instanceid":10038034},{"pos":{"x":520,"y":460},"bg":"bg_watertiles","sourcepos":{"x":80,"y":220},"size":{"width":20,"height":20},"scale":{"x":1.0,"y":1.0},"colour":"#FFFFFFFF","tiledepth":1000003,"instanceid":10038035},{"pos":{"x":520,"y":440},"bg":"bg_watertiles","sourcepos":{"x":80,"y":220},"size":{"width":20,"height":20},"scale":{"x":1.0,"y":1.0},"colour":"#FFFFFFFF","tiledepth":1000003,"instanceid":10038036},{"pos":{"x":520,"y":420},"bg":"bg_watertiles","sourcepos":{"x":80,"y":220},"size":{"width":20,"height":20},"scale":{"x":1.0,"y":1.0},"colour":"#FFFFFFFF","tiledepth":1000003,"instanceid":10038037},{"pos":{"x":520,"y":400},"bg":"bg_watertiles","sourcepos":{"x":80,"y":220},"size":{"width":20,"height":20},"scale":{"x":1.0,"y":1.0},"colour":"#FFFFFFFF","tiledepth":1000003,"instanceid":10038038},{"pos":{"x":320,"y":400},"bg":"bg_watertiles","sourcepos":{"x":80,"y":220},"size":{"width":20,"height":20},"scale":{"x":1.0,"y":1.0},"colour":"#FFFFFFFF","tiledepth":1000003,"instanceid":10038039},{"pos":{"x":320,"y":380},"bg":"bg_watertiles","sourcepos":{"x":80,"y":220},"size":{"width":20,"height":20},"scale":{"x":1.0,"y":1.0},"colour":"#FFFFFFFF","tiledepth":1000003,"instanceid":10038040},{"pos":{"x":320,"y":360},"bg":"bg_watertiles","sourcepos":{"x":80,"y":220},"size":{"width":20,"height":20},"scale":{"x":1.0,"y":1.0},"colour":"#FFFFFFFF","tiledepth":1000003,"instanceid":10038041},{"pos":{"x":340,"y":360},"bg":"bg_watertiles","sourcepos":{"x":80,"y":220},"size":{"width":20,"height":20},"scale":{"x":1.0,"y":1.0},"colour":"#FFFFFFFF","tiledepth":1000003,"instanceid":10038042},{"pos":{"x":360,"y":360},"bg":"bg_watertiles","sourcepos":{"x":80,"y":220},"size":{"width":20,"height":20},"scale":{"x":1.0,"y":1.0},"colour":"#FFFFFFFF","tiledepth":1000003,"instanceid":10038043},{"pos":{"x":360,"y":380},"bg":"bg_watertiles","sourcepos":{"x":80,"y":220},"size":{"width":20,"height":20},"scale":{"x":1.0,"y":1.0},"colour":"#FFFFFFFF","tiledepth":1000003,"instanceid":10038044},{"pos":{"x":360,"y":400},"bg":"bg_watertiles","sourcepos":{"x":80,"y":220},"size":{"width":20,"height":20},"scale":{"x":1.0,"y":1.0},"colour":"#FFFFFFFF","tiledepth":1000003,"instanceid":10038045},{"pos":{"x":340,"y":400},"bg":"bg_watertiles","sourcepos":{"x":80,"y":220},"size":{"width":20,"height":20},"scale":{"x":1.0,"y":1.0},"colour":"#FFFFFFFF","tiledepth":1000003,"instanceid":10038046},{"pos":{"x":520,"y":380},"bg":"bg_watertiles","sourcepos":{"x":80,"y":220},"size":{"width":20,"height":20},"scale":{"x":1.0,"y":1.0},"colour":"#FFFFFFFF","tiledepth":1000003,"instanceid":10038047},{"pos":{"x":500,"y":380},"bg":"bg_watertiles","sourcepos":{"x":80,"y":220},"size":{"width":20,"height":20},"scale":{"x":1.0,"y":1.0},"colour":"#FFFFFFFF","tiledepth":1000003,"instanceid":10038048},{"pos":{"x":480,"y":380},"bg":"bg_watertiles","sourcepos":{"x":80,"y":220},"size":{"width":20,"height":20},"scale":{"x":1.0,"y":1.0},"colour":"#FFFFFFFF","tiledepth":1000003,"instanceid":10038049},{"pos":{"x":460,"y":380},"bg":"bg_watertiles","sourcepos":{"x":80,"y":220},"size":{"width":20,"height":20},"scale":{"x":1.0,"y":1.0},"colour":"#FFFFFFFF","tiledepth":1000003,"instanceid":10038050},{"pos":{"x":240,"y":240},"bg":"bg_watertiles","sourcepos":{"x":80,"y":220},"size":{"width":20,"height":20},"scale":{"x":1.0,"y":1.0},"colour":"#FFFFFFFF","tiledepth":1000003,"instanceid":10038051},{"pos":{"x":260,"y":240},"bg":"bg_watertiles","sourcepos":{"x":80,"y":220},"size":{"width":20,"height":20},"scale":{"x":1.0,"y":1.0},"colour":"#FFFFFFFF","tiledepth":1000003,"instanceid":10038052},{"pos":{"x":280,"y":240},"bg":"bg_watertiles","sourcepos":{"x":80,"y":220},"size":{"width":20,"height":20},"scale":{"x":1.0,"y":1.0},"colour":"#FFFFFFFF","tiledepth":1000003,"instanceid":10038053},{"pos":{"x":300,"y":240},"bg":"bg_watertiles","sourcepos":{"x":80,"y":220},"size":{"width":20,"height":20},"scale":{"x":1.0,"y":1.0},"colour":"#FFFFFFFF","tiledepth":1000003,"instanceid":10038054},{"pos":{"x":320,"y":240},"bg":"bg_watertiles","sourcepos":{"x":80,"y":220},"size":{"width":20,"height":20},"scale":{"x":1.0,"y":1.0},"colour":"#FFFFFFFF","tiledepth":1000003,"instanceid":10038055},{"pos":{"x":340,"y":240},"bg":"bg_watertiles","sourcepos":{"x":80,"y":220},"size":{"width":20,"height":20},"scale":{"x":1.0,"y":1.0},"colour":"#FFFFFFFF","tiledepth":1000003,"instanceid":10038056},{"pos":{"x":340,"y":260},"bg":"bg_watertiles","sourcepos":{"x":80,"y":220},"size":{"width":20,"height":20},"scale":{"x":1.0,"y":1.0},"colour":"#FFFFFFFF","tiledepth":1000003,"instanceid":10038057},{"pos":{"x":340,"y":280},"bg":"bg_watertiles","sourcepos":{"x":80,"y":220},"size":{"width":20,"height":20},"scale":{"x":1.0,"y":1.0},"colour":"#FFFFFFFF","tiledepth":1000003,"instanceid":10038058},{"pos":{"x":340,"y":300},"bg":"bg_watertiles","sourcepos":{"x":80,"y":220},"size":{"width":20,"height":20},"scale":{"x":1.0,"y":1.0},"colour":"#FFFFFFFF","tiledepth":1000003,"instanceid":10038059},{"pos":{"x":340,"y":320},"bg":"bg_watertiles","sourcepos":{"x":80,"y":220},"size":{"width":20,"height":20},"scale":{"x":1.0,"y":1.0},"colour":"#FFFFFFFF","tiledepth":1000003,"instanceid":10038060},{"pos":{"x":340,"y":340},"bg":"bg_watertiles","sourcepos":{"x":80,"y":220},"size":{"width":20,"height":20},"scale":{"x":1.0,"y":1.0},"colour":"#FFFFFFFF","tiledepth":1000003,"instanceid":10038061},{"pos":{"x":200,"y":420},"bg":"bg_watertiles","sourcepos":{"x":80,"y":220},"size":{"width":20,"height":20},"scale":{"x":1.0,"y":1.0},"colour":"#FFFFFFFF","tiledepth":1000002,"instanceid":10038062},{"pos":{"x":200,"y":440},"bg":"bg_watertiles","sourcepos":{"x":80,"y":220},"size":{"width":20,"height":20},"scale":{"x":1.0,"y":1.0},"colour":"#FFFFFFFF","tiledepth":1000002,"instanceid":10038063},{"pos":{"x":200,"y":460},"bg":"bg_watertiles","sourcepos":{"x":80,"y":220},"size":{"width":20,"height":20},"scale":{"x":1.0,"y":1.0},"colour":"#FFFFFFFF","tiledepth":1000002,"instanceid":10038064},{"pos":{"x":200,"y":480},"bg":"bg_watertiles","sourcepos":{"x":80,"y":220},"size":{"width":20,"height":20},"scale":{"x":1.0,"y":1.0},"colour":"#FFFFFFFF","tiledepth":1000002,"instanceid":10038065},{"pos":{"x":200,"y":500},"bg":"bg_watertiles","sourcepos":{"x":80,"y":220},"size":{"width":20,"height":20},"scale":{"x":1.0,"y":1.0},"colour":"#FFFFFFFF","tiledepth":1000002,"instanceid":10038066},{"pos":{"x":200,"y":520},"bg":"bg_watertiles","sourcepos":{"x":80,"y":220},"size":{"width":20,"height":20},"scale":{"x":1.0,"y":1.0},"colour":"#FFFFFFFF","tiledepth":1000002,"instanceid":10038067},{"pos":{"x":200,"y":540},"bg":"bg_watertiles","sourcepos":{"x":80,"y":220},"size":{"width":20,"height":20},"scale":{"x":1.0,"y":1.0},"colour":"#FFFFFFFF","tiledepth":1000002,"instanceid":10038068},{"pos":{"x":220,"y":540},"bg":"bg_watertiles","sourcepos":{"x":80,"y":220},"size":{"width":20,"height":20},"scale":{"x":1.0,"y":1.0},"colour":"#FFFFFFFF","tiledepth":1000002,"instanceid":10038069},{"pos":{"x":240,"y":540},"bg":"bg_watertiles","sourcepos":{"x":80,"y":220},"size":{"width":20,"height":20},"scale":{"x":1.0,"y":1.0},"colour":"#FFFFFFFF","tiledepth":1000002,"instanceid":10038070},{"pos":{"x":260,"y":540},"bg":"bg_watertiles","sourcepos":{"x":80,"y":220},"size":{"width":20,"height":20},"scale":{"x":1.0,"y":1.0},"colour":"#FFFFFFFF","tiledepth":1000002,"instanceid":10038071},{"pos":{"x":280,"y":540},"bg":"bg_watertiles","sourcepos":{"x":80,"y":220},"size":{"width":20,"height":20},"scale":{"x":1.0,"y":1.0},"colour":"#FFFFFFFF","tiledepth":1000002,"instanceid":10038072},{"pos":{"x":300,"y":540},"bg":"bg_watertiles","sourcepos":{"x":80,"y":220},"size":{"width":20,"height":20},"scale":{"x":1.0,"y":1.0},"colour":"#FFFFFFFF","tiledepth":1000002,"instanceid":10038073},{"pos":{"x":320,"y":540},"bg":"bg_watertiles","sourcepos":{"x":80,"y":220},"size":{"width":20,"height":20},"scale":{"x":1.0,"y":1.0},"colour":"#FFFFFFFF","tiledepth":1000002,"instanceid":10038074},{"pos":{"x":320,"y":520},"bg":"bg_watertiles","sourcepos":{"x":80,"y":220},"size":{"width":20,"height":20},"scale":{"x":1.0,"y":1.0},"colour":"#FFFFFFFF","tiledepth":1000002,"instanceid":10038075},{"pos":{"x":340,"y":520},"bg":"bg_watertiles","sourcepos":{"x":80,"y":220},"size":{"width":20,"height":20},"scale":{"x":1.0,"y":1.0},"colour":"#FFFFFFFF","tiledepth":1000002,"instanceid":10038076},{"pos":{"x":360,"y":520},"bg":"bg_watertiles","sourcepos":{"x":80,"y":220},"size":{"width":20,"height":20},"scale":{"x":1.0,"y":1.0},"colour":"#FFFFFFFF","tiledepth":1000002,"instanceid":10038077},{"pos":{"x":360,"y":540},"bg":"bg_watertiles","sourcepos":{"x":80,"y":220},"size":{"width":20,"height":20},"scale":{"x":1.0,"y":1.0},"colour":"#FFFFFFFF","tiledepth":1000002,"instanceid":10038078},{"pos":{"x":360,"y":560},"bg":"bg_watertiles","sourcepos":{"x":80,"y":220},"size":{"width":20,"height":20},"scale":{"x":1.0,"y":1.0},"colour":"#FFFFFFFF","tiledepth":1000002,"instanceid":10038079},{"pos":{"x":340,"y":560},"bg":"bg_watertiles","sourcepos":{"x":80,"y":220},"size":{"width":20,"height":20},"scale":{"x":1.0,"y":1.0},"colour":"#FFFFFFFF","tiledepth":1000002,"instanceid":10038080},{"pos":{"x":320,"y":560},"bg":"bg_watertiles","sourcepos":{"x":80,"y":220},"size":{"width":20,"height":20},"scale":{"x":1.0,"y":1.0},"colour":"#FFFFFFFF","tiledepth":1000002,"instanceid":10038081},{"pos":{"x":160,"y":240},"bg":"bg_watertiles","sourcepos":{"x":80,"y":220},"size":{"width":20,"height":20},"scale":{"x":1.0,"y":1.0},"colour":"#FFFFFFFF","tiledepth":1000001,"instanceid":10038082},{"pos":{"x":140,"y":240},"bg":"bg_watertiles","sourcepos":{"x":80,"y":220},"size":{"width":20,"height":20},"scale":{"x":1.0,"y":1.0},"colour":"#FFFFFFFF","tiledepth":1000001,"instanceid":10038083},{"pos":{"x":120,"y":240},"bg":"bg_watertiles","sourcepos":{"x":80,"y":220},"size":{"width":20,"height":20},"scale":{"x":1.0,"y":1.0},"colour":"#FFFFFFFF","tiledepth":1000001,"instanceid":10038084},{"pos":{"x":100,"y":240},"bg":"bg_watertiles","sourcepos":{"x":80,"y":220},"size":{"width":20,"height":20},"scale":{"x":1.0,"y":1.0},"colour":"#FFFFFFFF","tiledepth":1000001,"instanceid":10038085},{"pos":{"x":80,"y":240},"bg":"bg_watertiles","sourcepos":{"x":80,"y":220},"size":{"width":20,"height":20},"scale":{"x":1.0,"y":1.0},"colour":"#FFFFFFFF","tiledepth":1000001,"instanceid":10038086},{"pos":{"x":60,"y":240},"bg":"bg_watertiles","sourcepos":{"x":80,"y":220},"size":{"width":20,"height":20},"scale":{"x":1.0,"y":1.0},"colour":"#FFFFFFFF","tiledepth":1000001,"instanceid":10038087},{"pos":{"x":60,"y":260},"bg":"bg_watertiles","sourcepos":{"x":80,"y":220},"size":{"width":20,"height":20},"scale":{"x":1.0,"y":1.0},"colour":"#FFFFFFFF","tiledepth":1000001,"instanceid":10038088},{"pos":{"x":60,"y":280},"bg":"bg_watertiles","sourcepos":{"x":80,"y":220},"size":{"width":20,"height":20},"scale":{"x":1.0,"y":1.0},"colour":"#FFFFFFFF","tiledepth":1000001,"instanceid":10038089},{"pos":{"x":60,"y":300},"bg":"bg_watertiles","sourcepos":{"x":80,"y":220},"size":{"width":20,"height":20},"scale":{"x":1.0,"y":1.0},"colour":"#FFFFFFFF","tiledepth":1000001,"instanceid":10038090},{"pos":{"x":60,"y":320},"bg":"bg_watertiles","sourcepos":{"x":80,"y":220},"size":{"width":20,"height":20},"scale":{"x":1.0,"y":1.0},"colour":"#FFFFFFFF","tiledepth":1000001,"instanceid":10038091},{"pos":{"x":60,"y":340},"bg":"bg_watertiles","sourcepos":{"x":80,"y":220},"size":{"width":20,"height":20},"scale":{"x":1.0,"y":1.0},"colour":"#FFFFFFFF","tiledepth":1000001,"instanceid":10038092},{"pos":{"x":60,"y":360},"bg":"bg_watertiles","sourcepos":{"x":80,"y":220},"size":{"width":20,"height":20},"scale":{"x":1.0,"y":1.0},"colour":"#FFFFFFFF","tiledepth":1000001,"instanceid":10038093},{"pos":{"x":60,"y":380},"bg":"bg_watertiles","sourcepos":{"x":80,"y":220},"size":{"width":20,"height":20},"scale":{"x":1.0,"y":1.0},"colour":"#FFFFFFFF","tiledepth":1000001,"instanceid":10038094},{"pos":{"x":80,"y":380},"bg":"bg_watertiles","sourcepos":{"x":80,"y":220},"size":{"width":20,"height":20},"scale":{"x":1.0,"y":1.0},"colour":"#FFFFFFFF","tiledepth":1000001,"instanceid":10038095},{"pos":{"x":100,"y":380},"bg":"bg_watertiles","sourcepos":{"x":80,"y":220},"size":{"width":20,"height":20},"scale":{"x":1.0,"y":1.0},"colour":"#FFFFFFFF","tiledepth":1000001,"instanceid":10038096},{"pos":{"x":120,"y":380},"bg":"bg_watertiles","sourcepos":{"x":80,"y":220},"size":{"width":20,"height":20},"scale":{"x":1.0,"y":1.0},"colour":"#FFFFFFFF","tiledepth":1000001,"instanceid":10038097},{"pos":{"x":140,"y":380},"bg":"bg_watertiles","sourcepos":{"x":80,"y":220},"size":{"width":20,"height":20},"scale":{"x":1.0,"y":1.0},"colour":"#FFFFFFFF","tiledepth":1000001,"instanceid":10038098},{"pos":{"x":160,"y":380},"bg":"bg_watertiles","sourcepos":{"x":80,"y":220},"size":{"width":20,"height":20},"scale":{"x":1.0,"y":1.0},"colour":"#FFFFFFFF","tiledepth":1000001,"instanceid":10038099},{"pos":{"x":180,"y":380},"bg":"bg_watertiles","sourcepos":{"x":80,"y":220},"size":{"width":20,"height":20},"scale":{"x":1.0,"y":1.0},"colour":"#FFFFFFFF","tiledepth":1000001,"instanceid":10038100},{"pos":{"x":180,"y":360},"bg":"bg_watertiles","sourcepos":{"x":80,"y":220},"size":{"width":20,"height":20},"scale":{"x":1.0,"y":1.0},"colour":"#FFFFFFFF","tiledepth":1000001,"instanceid":10038101},{"pos":{"x":200,"y":360},"bg":"bg_watertiles","sourcepos":{"x":80,"y":220},"size":{"width":20,"height":20},"scale":{"x":1.0,"y":1.0},"colour":"#FFFFFFFF","tiledepth":1000001,"instanceid":10038102},{"pos":{"x":220,"y":360},"bg":"bg_watertiles","sourcepos":{"x":80,"y":220},"size":{"width":20,"height":20},"scale":{"x":1.0,"y":1.0},"colour":"#FFFFFFFF","tiledepth":1000001,"instanceid":10038103},{"pos":{"x":220,"y":380},"bg":"bg_watertiles","sourcepos":{"x":80,"y":220},"size":{"width":20,"height":20},"scale":{"x":1.0,"y":1.0},"colour":"#FFFFFFFF","tiledepth":1000001,"instanceid":10038104},{"pos":{"x":220,"y":400},"bg":"bg_watertiles","sourcepos":{"x":80,"y":220},"size":{"width":20,"height":20},"scale":{"x":1.0,"y":1.0},"colour":"#FFFFFFFF","tiledepth":1000001,"instanceid":10038105},{"pos":{"x":200,"y":400},"bg":"bg_watertiles","sourcepos":{"x":80,"y":220},"size":{"width":20,"height":20},"scale":{"x":1.0,"y":1.0},"colour":"#FFFFFFFF","tiledepth":1000001,"instanceid":10038106},{"pos":{"x":180,"y":400},"bg":"bg_watertiles","sourcepos":{"x":80,"y":220},"size":{"width":20,"height":20},"scale":{"x":1.0,"y":1.0},"colour":"#FFFFFFFF","tiledepth":1000001,"instanceid":10038107},{"pos":{"x":0,"y":100},"bg":"bg_watertiles","sourcepos":{"x":40,"y":160},"size":{"width":20,"height":20},"scale":{"x":1.0,"y":1.0},"colour":"#FFFFFFFF","tiledepth":1000000,"instanceid":10038108},{"pos":{"x":20,"y":100},"bg":"bg_watertiles","sourcepos":{"x":40,"y":160},"size":{"width":20,"height":20},"scale":{"x":1.0,"y":1.0},"colour":"#FFFFFFFF","tiledepth":1000000,"instanceid":10038109},{"pos":{"x":0,"y":120},"bg":"bg_watertiles","sourcepos":{"x":40,"y":160},"size":{"width":20,"height":20},"scale":{"x":1.0,"y":1.0},"colour":"#FFFFFFFF","tiledepth":1000000,"instanceid":10038110},{"pos":{"x":20,"y":120},"bg":"bg_watertiles","sourcepos":{"x":40,"y":160},"size":{"width":20,"height":20},"scale":{"x":1.0,"y":1.0},"colour":"#FFFFFFFF","tiledepth":1000000,"instanceid":10038111},{"pos":{"x":40,"y":120},"bg":"bg_watertiles","sourcepos":{"x":40,"y":160},"size":{"width":20,"height":20},"scale":{"x":1.0,"y":1.0},"colour":"#FFFFFFFF","tiledepth":1000000,"instanceid":10038112},{"pos":{"x":40,"y":100},"bg":"bg_watertiles","sourcepos":{"x":40,"y":160},"size":{"width":20,"height":20},"scale":{"x":1.0,"y":1.0},"colour":"#FFFFFFFF","tiledepth":1000000,"instanceid":10038113},{"pos":{"x":60,"y":100},"bg":"bg_watertiles","sourcepos":{"x":40,"y":160},"size":{"width":20,"height":20},"scale":{"x":1.0,"y":1.0},"colour":"#FFFFFFFF","tiledepth":1000000,"instanceid":10038114},{"pos":{"x":60,"y":120},"bg":"bg_watertiles","sourcepos":{"x":40,"y":160},"size":{"width":20,"height":20},"scale":{"x":1.0,"y":1.0},"colour":"#FFFFFFFF","tiledepth":1000000,"instanceid":10038115},{"pos":{"x":80,"y":120},"bg":"bg_watertiles","sourcepos":{"x":40,"y":160},"size":{"width":20,"height":20},"scale":{"x":1.0,"y":1.0},"colour":"#FFFFFFFF","tiledepth":1000000,"instanceid":10038116},{"pos":{"x":100,"y":120},"bg":"bg_watertiles","sourcepos":{"x":40,"y":160},"size":{"width":20,"height":20},"scale":{"x":1.0,"y":1.0},"colour":"#FFFFFFFF","tiledepth":1000000,"instanceid":10038117},{"pos":{"x":120,"y":120},"bg":"bg_watertiles","sourcepos":{"x":40,"y":160},"size":{"width":20,"height":20},"scale":{"x":1.0,"y":1.0},"colour":"#FFFFFFFF","tiledepth":1000000,"instanceid":10038118},{"pos":{"x":140,"y":120},"bg":"bg_watertiles","sourcepos":{"x":40,"y":160},"size":{"width":20,"height":20},"scale":{"x":1.0,"y":1.0},"colour":"#FFFFFFFF","tiledepth":1000000,"instanceid":10038119},{"pos":{"x":160,"y":120},"bg":"bg_watertiles","sourcepos":{"x":40,"y":160},"size":{"width":20,"height":20},"scale":{"x":1.0,"y":1.0},"colour":"#FFFFFFFF","tiledepth":1000000,"instanceid":10038120},{"pos":{"x":180,"y":120},"bg":"bg_watertiles","sourcepos":{"x":40,"y":160},"size":{"width":20,"height":20},"scale":{"x":1.0,"y":1.0},"colour":"#FFFFFFFF","tiledepth":1000000,"instanceid":10038121},{"pos":{"x":200,"y":120},"bg":"bg_watertiles","sourcepos":{"x":40,"y":160},"size":{"width":20,"height":20},"scale":{"x":1.0,"y":1.0},"colour":"#FFFFFFFF","tiledepth":1000000,"instanceid":10038122},{"pos":{"x":200,"y":100},"bg":"bg_watertiles","sourcepos":{"x":40,"y":160},"size":{"width":20,"height":20},"scale":{"x":1.0,"y":1.0},"colour":"#FFFFFFFF","tiledepth":1000000,"instanceid":10038123},{"pos":{"x":180,"y":100},"bg":"bg_watertiles","sourcepos":{"x":40,"y":160},"size":{"width":20,"height":20},"scale":{"x":1.0,"y":1.0},"colour":"#FFFFFFFF","tiledepth":1000000,"instanceid":10038124},{"pos":{"x":160,"y":100},"bg":"bg_watertiles","sourcepos":{"x":40,"y":160},"size":{"width":20,"height":20},"scale":{"x":1.0,"y":1.0},"colour":"#FFFFFFFF","tiledepth":1000000,"instanceid":10038125},{"pos":{"x":140,"y":100},"bg":"bg_watertiles","sourcepos":{"x":40,"y":160},"size":{"width":20,"height":20},"scale":{"x":1.0,"y":1.0},"colour":"#FFFFFFFF","tiledepth":1000000,"instanceid":10038126},{"pos":{"x":120,"y":100},"bg":"bg_watertiles","sourcepos":{"x":40,"y":160},"size":{"width":20,"height":20},"scale":{"x":1.0,"y":1.0},"colour":"#FFFFFFFF","tiledepth":1000000,"instanceid":10038127},{"pos":{"x":100,"y":100},"bg":"bg_watertiles","sourcepos":{"x":40,"y":160},"size":{"width":20,"height":20},"scale":{"x":1.0,"y":1.0},"colour":"#FFFFFFFF","tiledepth":1000000,"instanceid":10038128},{"pos":{"x":80,"y":100},"bg":"bg_watertiles","sourcepos":{"x":40,"y":160},"size":{"width":20,"height":20},"scale":{"x":1.0,"y":1.0},"colour":"#FFFFFFFF","tiledepth":1000000,"instanceid":10038129},{"pos":{"x":200,"y":140},"bg":"bg_watertiles","sourcepos":{"x":80,"y":220},"size":{"width":20,"height":20},"scale":{"x":1.0,"y":1.0},"colour":"#FFFFFFFF","tiledepth":1000000,"instanceid":10038130},{"pos":{"x":200,"y":160},"bg":"bg_watertiles","sourcepos":{"x":80,"y":220},"size":{"width":20,"height":20},"scale":{"x":1.0,"y":1.0},"colour":"#FFFFFFFF","tiledepth":1000000,"instanceid":10038131},{"pos":{"x":200,"y":180},"bg":"bg_watertiles","sourcepos":{"x":80,"y":220},"size":{"width":20,"height":20},"scale":{"x":1.0,"y":1.0},"colour":"#FFFFFFFF","tiledepth":1000000,"instanceid":10038132},{"pos":{"x":200,"y":200},"bg":"bg_watertiles","sourcepos":{"x":80,"y":220},"size":{"width":20,"height":20},"scale":{"x":1.0,"y":1.0},"colour":"#FFFFFFFF","tiledepth":1000000,"instanceid":10038133},{"pos":{"x":200,"y":220},"bg":"bg_watertiles","sourcepos":{"x":80,"y":220},"size":{"width":20,"height":20},"scale":{"x":1.0,"y":1.0},"colour":"#FFFFFFFF","tiledepth":1000000,"instanceid":10038134},{"pos":{"x":180,"y":220},"bg":"bg_watertiles","sourcepos":{"x":80,"y":220},"size":{"width":20,"height":20},"scale":{"x":1.0,"y":1.0},"colour":"#FFFFFFFF","tiledepth":1000000,"instanceid":10038135},{"pos":{"x":180,"y":240},"bg":"bg_watertiles","sourcepos":{"x":80,"y":220},"size":{"width":20,"height":20},"scale":{"x":1.0,"y":1.0},"colour":"#FFFFFFFF","tiledepth":1000000,"instanceid":10038136},{"pos":{"x":180,"y":260},"bg":"bg_watertiles","sourcepos":{"x":80,"y":220},"size":{"width":20,"height":20},"scale":{"x":1.0,"y":1.0},"colour":"#FFFFFFFF","tiledepth":1000000,"instanceid":10038137},{"pos":{"x":200,"y":260},"bg":"bg_watertiles","sourcepos":{"x":80,"y":220},"size":{"width":20,"height":20},"scale":{"x":1.0,"y":1.0},"colour":"#FFFFFFFF","tiledepth":1000000,"instanceid":10038138},{"pos":{"x":220,"y":260},"bg":"bg_watertiles","sourcepos":{"x":80,"y":220},"size":{"width":20,"height":20},"scale":{"x":1.0,"y":1.0},"colour":"#FFFFFFFF","tiledepth":1000000,"instanceid":10038139},{"pos":{"x":220,"y":240},"bg":"bg_watertiles","sourcepos":{"x":80,"y":220},"size":{"width":20,"height":20},"scale":{"x":1.0,"y":1.0},"colour":"#FFFFFFFF","tiledepth":1000000,"instanceid":10038140},{"pos":{"x":220,"y":220},"bg":"bg_watertiles","sourcepos":{"x":80,"y":220},"size":{"width":20,"height":20},"scale":{"x":1.0,"y":1.0},"colour":"#FFFFFFFF","tiledepth":1000000,"instanceid":10038141},{"pos":{"x":120,"y":265},"bg":"bg_watertiles_2","sourcepos":{"x":260,"y":200},"size":{"width":20,"height":80},"scale":{"x":1.0,"y":1.0},"colour":"#FFFFFFFF","tiledepth":3004,"instanceid":10038142},{"pos":{"x":510,"y":265},"bg":"bg_watertiles_2","sourcepos":{"x":260,"y":200},"size":{"width":20,"height":80},"scale":{"x":1.0,"y":1.0},"colour":"#FFFFFFFF","tiledepth":3004,"instanceid":10038143},{"pos":{"x":430,"y":130},"bg":"bg_watertiles_2","sourcepos":{"x":260,"y":200},"size":{"width":20,"height":80},"scale":{"x":1.0,"y":1.0},"colour":"#FFFFFFFF","tiledepth":3004,"instanceid":10038144},{"pos":{"x":270,"y":425},"bg":"bg_watertiles_2","sourcepos":{"x":260,"y":200},"size":{"width":20,"height":80},"scale":{"x":1.0,"y":1.0},"colour":"#FFFFFFFF","tiledepth":3004,"instanceid":10038145},{"pos":{"x":450,"y":430},"bg":"bg_watertiles_2","sourcepos":{"x":260,"y":200},"size":{"width":20,"height":80},"scale":{"x":1.0,"y":1.0},"colour":"#FFFFFFFF","tiledepth":3004,"instanceid":10038146},{"pos":{"x":285,"y":130},"bg":"bg_watertiles_2","sourcepos":{"x":260,"y":200},"size":{"width":20,"height":80},"scale":{"x":1.0,"y":1.0},"colour":"#FFFFFFFF","tiledepth":3004,"instanceid":10038147},{"pos":{"x":270,"y":270},"bg":"bg_watertiles_2","sourcepos":{"x":260,"y":200},"size":{"width":20,"height":80},"scale":{"x":1.0,"y":1.0},"colour":"#FFFFFFFF","tiledepth":3004,"instanceid":10038148},{"pos":{"x":120,"y":430},"bg":"bg_watertiles_2","sourcepos":{"x":260,"y":200},"size":{"width":20,"height":80},"scale":{"x":1.0,"y":1.0},"colour":"#FFFFFFFF","tiledepth":3004,"instanceid":10038149}]}