{"caption":"","size":{"width":320,"height":240},"speed":30,"persist":false,"colour":"#00000000","enableviews":true,"showcolour":true,"clearbuf":false,"world":0,"bounding":{"top":0,"left":0,"bottom":768,"right":1024},"gravity":{"x":0.0,"y":10.0},"metresperpx":0.100000001490116,"drawbgcol":true,"bgs":[{"enabled":false,"foreground":false,"pos":{"x":0,"y":0},"tilex":true,"tiley":true,"speed":{"x":0,"y":0},"stretch":false},{"enabled":false,"foreground":false,"pos":{"x":0,"y":0},"tilex":true,"tiley":true,"speed":{"x":0,"y":0},"stretch":false},{"enabled":false,"foreground":false,"pos":{"x":0,"y":0},"tilex":true,"tiley":true,"speed":{"x":0,"y":0},"stretch":false},{"enabled":false,"foreground":false,"pos":{"x":0,"y":0},"tilex":true,"tiley":true,"speed":{"x":0,"y":0},"stretch":false},{"enabled":false,"foreground":false,"pos":{"x":0,"y":0},"tilex":true,"tiley":true,"speed":{"x":0,"y":0},"stretch":false},{"enabled":false,"foreground":false,"pos":{"x":0,"y":0},"tilex":true,"tiley":true,"speed":{"x":0,"y":0},"stretch":false},{"enabled":false,"foreground":false,"pos":{"x":0,"y":0},"tilex":true,"tiley":true,"speed":{"x":0,"y":0},"stretch":false},{"enabled":false,"foreground":false,"pos":{"x":0,"y":0},"tilex":true,"tiley":true,"speed":{"x":0,"y":0},"stretch":false}],"views":[{"enabled":true,"view":{"x":0,"y":0,"width":320,"height":240},"port":{"x":0,"y":0,"width":640,"height":480},"border":{"x":32,"y":32},"speed":{"x":-1,"y":-1},"obj":"obj_mainchara"},{"enabled":false,"view":{"x":0,"y":0,"width":640,"height":480},"port":{"x":0,"y":0,"width":640,"height":480},"border":{"x":32,"y":32},"speed":{"x":-1,"y":-1}},{"enabled":false,"view":{"x":0,"y":0,"width":640,"height":480},"port":{"x":0,"y":0,"width":640,"height":480},"border":{"x":32,"y":32},"speed":{"x":-1,"y":-1}},{"enabled":false,"view":{"x":0,"y":0,"width":640,"height":480},"port":{"x":0,"y":0,"width":640,"height":480},"border":{"x":32,"y":32},"speed":{"x":-1,"y":-1}},{"enabled":false,"view":{"x":0,"y":0,"width":640,"height":480},"port":{"x":0,"y":0,"width":640,"height":480},"border":{"x":32,"y":32},"speed":{"x":-1,"y":-1}},{"enabled":false,"view":{"x":0,"y":0,"width":640,"height":480},"port":{"x":0,"y":0,"width":640,"height":480},"border":{"x":32,"y":32},"speed":{"x":-1,"y":-1}},{"enabled":false,"view":{"x":0,"y":0,"width":640,"height":480},"port":{"x":0,"y":0,"width":640,"height":480},"border":{"x":32,"y":32},"speed":{"x":-1,"y":-1}},{"enabled":false,"view":{"x":0,"y":0,"width":640,"height":480},"port":{"x":0,"y":0,"width":640,"height":480},"border":{"x":32,"y":32},"speed":{"x":-1,"y":-1}}],"objs":[{"pos":{"x":110,"y":108},"obj":"obj_mousehole","scale":{"x":1.0,"y":1.0},"colour":"#FFFFFFFF","rotation":0.0,"instanceid":100676,"createcodeid":4294967295},{"pos":{"x":100,"y":200},"obj":"obj_solidwide","scale":{"x":1.0,"y":1.0},"colour":"#FFFFFFFF","rotation":0.0,"instanceid":100677,"createcodeid":4294967295},{"pos":{"x":180,"y":200},"obj":"obj_solidwide","scale":{"x":1.0,"y":1.0},"colour":"#FFFFFFFF","rotation":0.0,"instanceid":100678,"createcodeid":4294967295},{"pos":{"x":0,"y":100},"obj":"obj_solidlong","scale":{"x":1.0,"y":1.0},"colour":"#FFFFFFFF","rotation":0.0,"instanceid":100679,"createcodeid":4294967295},{"pos":{"x":80,"y":200},"obj":"obj_solidsmall","scale":{"x":1.0,"y":1.0},"colour":"#FFFFFFFF","rotation":0.0,"instanceid":100680,"createcodeid":4294967295},{"pos":{"x":220,"y":200},"obj":"obj_solidsmall","scale":{"x":1.0,"y":1.0},"colour":"#FFFFFFFF","rotation":0.0,"instanceid":100681,"createcodeid":4294967295},{"pos":{"x":0,"y":160},"obj":"obj_solidwide","scale":{"x":1.0,"y":1.0},"colour":"#FFFFFFFF","rotation":0.0,"instanceid":100682,"createcodeid":4294967295},{"pos":{"x":40,"y":160},"obj":"obj_solidwide","scale":{"x":1.0,"y":1.0},"colour":"#FFFFFFFF","rotation":0.0,"instanceid":100683,"createcodeid":4294967295},{"pos":{"x":240,"y":160},"obj":"obj_solidwide","scale":{"x":1.0,"y":1.0},"colour":"#FFFFFFFF","rotation":0.0,"instanceid":100684,"createcodeid":4294967295},{"pos":{"x":280,"y":160},"obj":"obj_solidwide","scale":{"x":1.0,"y":1.0},"colour":"#FFFFFFFF","rotation":0.0,"instanceid":100685,"createcodeid":4294967295},{"pos":{"x":140,"y":200},"obj":"obj_solidwide","scale":{"x":1.0,"y":1.0},"colour":"#FFFFFFFF","rotation":0.0,"instanceid":100686,"createcodeid":4294967295},{"pos":{"x":60,"y":180},"obj":"obj_solidtall_2","scale":{"x":1.0,"y":1.0},"colour":"#FFFFFFFF","rotation":0.0,"instanceid":100687,"createcodeid":4294967295},{"pos":{"x":240,"y":180},"obj":"obj_solidtall_2","scale":{"x":1.0,"y":1.0},"colour":"#FFFFFFFF","rotation":0.0,"instanceid":100688,"createcodeid":4294967295},{"pos":{"x":130,"y":150},"obj":"obj_mainchara","scale":{"x":1.0,"y":1.0},"colour":"#FFFFFFFF","rotation":0.0,"instanceid":100689,"createcodeid":4294967295},{"pos":{"x":110,"y":160},"obj":"obj_savepoint","scale":{"x":1.0,"y":1.0},"colour":"#FFFFFFFF","rotation":0.0,"instanceid":100690,"createcodeid":4294967295},{"pos":{"x":0,"y":120},"obj":"obj_doorB","scale":{"x":1.0,"y":1.0},"colour":"#FFFFFFFF","rotation":0.0,"instanceid":100691,"createcodeid":4294967295},{"pos":{"x":0,"y":140},"obj":"obj_doorB","scale":{"x":1.0,"y":1.0},"colour":"#FFFFFFFF","rotation":0.0,"instanceid":100692,"createcodeid":4294967295},{"pos":{"x":20,"y":120},"obj":"obj_markerA","scale":{"x":1.0,"y":1.0},"colour":"#FFFFFFFF","rotation":0.0,"instanceid":100693,"createcodeid":4294967295},{"pos":{"x":180,"y":160},"obj":"obj_cheesetable1","scale":{"x":1.0,"y":1.0},"colour":"#FFFFFFFF","rotation":0.0,"instanceid":100694,"createcodeid":4294967295},{"pos":{"x":66,"y":20},"obj":"obj_ruinsmusic","scale":{"x":1.0,"y":1.0},"colour":"#FFFFFFFF","rotation":0.0,"instanceid":100695,"createcodeid":4294967295},{"pos":{"x":300,"y":120},"obj":"obj_doorA","scale":{"x":1.0,"y":1.0},"colour":"#FFFFFFFF","rotation":0.0,"instanceid":100696,"createcodeid":4294967295},{"pos":{"x":300,"y":140},"obj":"obj_doorA","scale":{"x":1.0,"y":1.0},"colour":"#FFFFFFFF","rotation":0.0,"instanceid":100697,"createcodeid":4294967295},{"pos":{"x":280,"y":120},"obj":"obj_markerB","scale":{"x":1.0,"y":1.0},"colour":"#FFFFFFFF","rotation":0.0,"instanceid":100698,"createcodeid":4294967295},{"pos":{"x":20,"y":20},"obj":"obj_overworldcontroller","scale":{"x":1.0,"y":1.0},"colour":"#FFFFFFFF","rotation":0.0,"instanceid":100699,"createcodeid":4294967295}],"tiles":[{"pos":{"x":100,"y":180},"bg":"bg_ruinsplaceholder2","sourcepos":{"x":0,"y":0},"size":{"width":20,"height":20},"scale":{"x":1.0,"y":1.0},"colour":"#FFFFFFFF","tiledepth":1000000,"instanceid":10005136},{"pos":{"x":120,"y":180},"bg":"bg_ruinsplaceholder2","sourcepos":{"x":0,"y":0},"size":{"width":20,"height":20},"scale":{"x":1.0,"y":1.0},"colour":"#FFFFFFFF","tiledepth":1000000,"instanceid":10005137},{"pos":{"x":180,"y":180},"bg":"bg_ruinsplaceholder2","sourcepos":{"x":0,"y":0},"size":{"width":20,"height":20},"scale":{"x":1.0,"y":1.0},"colour":"#FFFFFFFF","tiledepth":1000000,"instanceid":10005138},{"pos":{"x":200,"y":180},"bg":"bg_ruinsplaceholder2","sourcepos":{"x":0,"y":0},"size":{"width":20,"height":20},"scale":{"x":1.0,"y":1.0},"colour":"#FFFFFFFF","tiledepth":1000000,"instanceid":10005139},{"pos":{"x":200,"y":160},"bg":"bg_ruinsplaceholder2","sourcepos":{"x":0,"y":0},"size":{"width":20,"height":20},"scale":{"x":1.0,"y":1.0},"colour":"#FFFFFFFF","tiledepth":1000000,"instanceid":10005140},{"pos":{"x":200,"y":140},"bg":"bg_ruinsplaceholder2","sourcepos":{"x":0,"y":0},"size":{"width":20,"height":20},"scale":{"x":1.0,"y":1.0},"colour":"#FFFFFFFF","tiledepth":1000000,"instanceid":10005141},{"pos":{"x":100,"y":140},"bg":"bg_ruinsplaceholder2","sourcepos":{"x":0,"y":0},"size":{"width":20,"height":20},"scale":{"x":1.0,"y":1.0},"colour":"#FFFFFFFF","tiledepth":1000000,"instanceid":10005142},{"pos":{"x":100,"y":160},"bg":"bg_ruinsplaceholder2","sourcepos":{"x":0,"y":0},"size":{"width":20,"height":20},"scale":{"x":1.0,"y":1.0},"colour":"#FFFFFFFF","tiledepth":1000000,"instanceid":10005143},{"pos":{"x":160,"y":140},"bg":"bg_ruinsplaceholder2","sourcepos":{"x":0,"y":0},"size":{"width":20,"height":20},"scale":{"x":1.0,"y":1.0},"colour":"#FFFFFFFF","tiledepth":1000000,"instanceid":10005144},{"pos":{"x":180,"y":140},"bg":"bg_ruinsplaceholder2","sourcepos":{"x":0,"y":0},"size":{"width":20,"height":20},"scale":{"x":1.0,"y":1.0},"colour":"#FFFFFFFF","tiledepth":1000000,"instanceid":10005145},{"pos":{"x":180,"y":160},"bg":"bg_ruinsplaceholder2","sourcepos":{"x":0,"y":0},"size":{"width":20,"height":20},"scale":{"x":1.0,"y":1.0},"colour":"#FFFFFFFF","tiledepth":1000000,"instanceid":10005146},{"pos":{"x":120,"y":140},"bg":"bg_ruinsplaceholder2","sourcepos":{"x":0,"y":0},"size":{"width":20,"height":20},"scale":{"x":1.0,"y":1.0},"colour":"#FFFFFFFF","tiledepth":1000000,"instanceid":10005147},{"pos":{"x":140,"y":140},"bg":"bg_ruinsplaceholder2","sourcepos":{"x":0,"y":0},"size":{"width":20,"height":20},"scale":{"x":1.0,"y":1.0},"colour":"#FFFFFFFF","tiledepth":1000000,"instanceid":10005148},{"pos":{"x":160,"y":160},"bg":"bg_ruinsplaceholder2","sourcepos":{"x":0,"y":0},"size":{"width":20,"height":20},"scale":{"x":1.0,"y":1.0},"colour":"#FFFFFFFF","tiledepth":1000000,"instanceid":10005149},{"pos":{"x":140,"y":160},"bg":"bg_ruinsplaceholder2","sourcepos":{"x":0,"y":0},"size":{"width":20,"height":20},"scale":{"x":1.0,"y":1.0},"colour":"#FFFFFFFF","tiledepth":1000000,"instanceid":10005150},{"pos":{"x":120,"y":160},"bg":"bg_ruinsplaceholder2","sourcepos":{"x":0,"y":0},"size":{"width":20,"height":20},"scale":{"x":1.0,"y":1.0},"colour":"#FFFFFFFF","tiledepth":1000000,"instanceid":10005151},{"pos":{"x":80,"y":180},"bg":"bg_ruinsplaceholder2","sourcepos":{"x":0,"y":0},"size":{"width":20,"height":20},"scale":{"x":1.0,"y":1.0},"colour":"#FFFFFFFF","tiledepth":1000000,"instanceid":10005152},{"pos":{"x":80,"y":160},"bg":"bg_ruinsplaceholder2","sourcepos":{"x":0,"y":0},"size":{"width":20,"height":20},"scale":{"x":1.0,"y":1.0},"colour":"#FFFFFFFF","tiledepth":1000000,"instanceid":10005153},{"pos":{"x":100,"y":120},"bg":"bg_ruinsplaceholder2","sourcepos":{"x":0,"y":0},"size":{"width":20,"height":20},"scale":{"x":1.0,"y":1.0},"colour":"#FFFFFFFF","tiledepth":1000000,"instanceid":10005154},{"pos":{"x":120,"y":120},"bg":"bg_ruinsplaceholder2","sourcepos":{"x":0,"y":0},"size":{"width":20,"height":20},"scale":{"x":1.0,"y":1.0},"colour":"#FFFFFFFF","tiledepth":1000000,"instanceid":10005155},{"pos":{"x":140,"y":120},"bg":"bg_ruinsplaceholder2","sourcepos":{"x":0,"y":0},"size":{"width":20,"height":20},"scale":{"x":1.0,"y":1.0},"colour":"#FFFFFFFF","tiledepth":1000000,"instanceid":10005156},{"pos":{"x":160,"y":120},"bg":"bg_ruinsplaceholder2","sourcepos":{"x":0,"y":0},"size":{"width":20,"height":20},"scale":{"x":1.0,"y":1.0},"colour":"#FFFFFFFF","tiledepth":1000000,"instanceid":10005157},{"pos":{"x":180,"y":120},"bg":"bg_ruinsplaceholder2","sourcepos":{"x":0,"y":0},"size":{"width":20,"height":20},"scale":{"x":1.0,"y":1.0},"colour":"#FFFFFFFF","tiledepth":1000000,"instanceid":10005158},{"pos":{"x":200,"y":120},"bg":"bg_ruinsplaceholder2","sourcepos":{"x":0,"y":0},"size":{"width":20,"height":20},"scale":{"x":1.0,"y":1.0},"colour":"#FFFFFFFF","tiledepth":1000000,"instanceid":10005159},{"pos":{"x":220,"y":160},"bg":"bg_ruinsplaceholder2","sourcepos":{"x":0,"y":0},"size":{"width":20,"height":20},"scale":{"x":1.0,"y":1.0},"colour":"#FFFFFFFF","tiledepth":1000000,"instanceid":10005160},{"pos":{"x":220,"y":180},"bg":"bg_ruinsplaceholder2","sourcepos":{"x":0,"y":0},"size":{"width":20,"height":20},"scale":{"x":1.0,"y":1.0},"colour":"#FFFFFFFF","tiledepth":1000000,"instanceid":10005161},{"pos":{"x":100,"y":60},"bg":"bg_ruinseasynam1","sourcepos":{"x":40,"y":0},"size":{"width":20,"height":20},"scale":{"x":1.0,"y":1.0},"colour":"#FFFFFFFF","tiledepth":1000000,"instanceid":10005162},{"pos":{"x":180,"y":60},"bg":"bg_ruinseasynam1","sourcepos":{"x":40,"y":0},"size":{"width":20,"height":20},"scale":{"x":1.0,"y":1.0},"colour":"#FFFFFFFF","tiledepth":1000000,"instanceid":10005163},{"pos":{"x":200,"y":60},"bg":"bg_ruinseasynam1","sourcepos":{"x":40,"y":0},"size":{"width":20,"height":20},"scale":{"x":1.0,"y":1.0},"colour":"#FFFFFFFF","tiledepth":1000000,"instanceid":10005164},{"pos":{"x":160,"y":60},"bg":"bg_ruinseasynam1","sourcepos":{"x":40,"y":0},"size":{"width":20,"height":20},"scale":{"x":1.0,"y":1.0},"colour":"#FFFFFFFF","tiledepth":1000000,"instanceid":10005165},{"pos":{"x":120,"y":60},"bg":"bg_ruinseasynam1","sourcepos":{"x":40,"y":0},"size":{"width":20,"height":20},"scale":{"x":1.0,"y":1.0},"colour":"#FFFFFFFF","tiledepth":1000000,"instanceid":10005166},{"pos":{"x":100,"y":80},"bg":"bg_ruinseasynam1","sourcepos":{"x":40,"y":0},"size":{"width":20,"height":20},"scale":{"x":1.0,"y":1.0},"colour":"#FFFFFFFF","tiledepth":1000000,"instanceid":10005167},{"pos":{"x":120,"y":80},"bg":"bg_ruinseasynam1","sourcepos":{"x":40,"y":0},"size":{"width":20,"height":20},"scale":{"x":1.0,"y":1.0},"colour":"#FFFFFFFF","tiledepth":1000000,"instanceid":10005168},{"pos":{"x":140,"y":80},"bg":"bg_ruinseasynam1","sourcepos":{"x":40,"y":0},"size":{"width":20,"height":20},"scale":{"x":1.0,"y":1.0},"colour":"#FFFFFFFF","tiledepth":1000000,"instanceid":10005169},{"pos":{"x":160,"y":80},"bg":"bg_ruinseasynam1","sourcepos":{"x":40,"y":0},"size":{"width":20,"height":20},"scale":{"x":1.0,"y":1.0},"colour":"#FFFFFFFF","tiledepth":1000000,"instanceid":10005170},{"pos":{"x":180,"y":80},"bg":"bg_ruinseasynam1","sourcepos":{"x":40,"y":0},"size":{"width":20,"height":20},"scale":{"x":1.0,"y":1.0},"colour":"#FFFFFFFF","tiledepth":1000000,"instanceid":10005171},{"pos":{"x":200,"y":80},"bg":"bg_ruinseasynam1","sourcepos":{"x":40,"y":0},"size":{"width":20,"height":20},"scale":{"x":1.0,"y":1.0},"colour":"#FFFFFFFF","tiledepth":1000000,"instanceid":10005172},{"pos":{"x":100,"y":200},"bg":"bg_ruinseasynam1","sourcepos":{"x":120,"y":0},"size":{"width":20,"height":20},"scale":{"x":1.0,"y":1.0},"colour":"#FFFFFFFF","tiledepth":1000000,"instanceid":10005173},{"pos":{"x":80,"y":200},"bg":"bg_ruinseasynam1","sourcepos":{"x":120,"y":0},"size":{"width":20,"height":20},"scale":{"x":1.0,"y":1.0},"colour":"#FFFFFFFF","tiledepth":1000000,"instanceid":10005174},{"pos":{"x":200,"y":200},"bg":"bg_ruinseasynam1","sourcepos":{"x":120,"y":0},"size":{"width":20,"height":20},"scale":{"x":1.0,"y":1.0},"colour":"#FFFFFFFF","tiledepth":1000000,"instanceid":10005175},{"pos":{"x":220,"y":200},"bg":"bg_ruinseasynam1","sourcepos":{"x":120,"y":0},"size":{"width":20,"height":20},"scale":{"x":1.0,"y":1.0},"colour":"#FFFFFFFF","tiledepth":1000000,"instanceid":10005176},{"pos":{"x":60,"y":180},"bg":"bg_ruinseasynam1","sourcepos":{"x":140,"y":20},"size":{"width":20,"height":20},"scale":{"x":1.0,"y":1.0},"colour":"#FFFFFFFF","tiledepth":1000000,"instanceid":10005177},{"pos":{"x":240,"y":180},"bg":"bg_ruinseasynam1","sourcepos":{"x":100,"y":20},"size":{"width":20,"height":20},"scale":{"x":1.0,"y":1.0},"colour":"#FFFFFFFF","tiledepth":1000000,"instanceid":10005178},{"pos":{"x":100,"y":40},"bg":"bg_ruinseasynam1","sourcepos":{"x":120,"y":40},"size":{"width":20,"height":20},"scale":{"x":1.0,"y":1.0},"colour":"#FFFFFFFF","tiledepth":1000000,"instanceid":10005179},{"pos":{"x":120,"y":40},"bg":"bg_ruinseasynam1","sourcepos":{"x":120,"y":40},"size":{"width":20,"height":20},"scale":{"x":1.0,"y":1.0},"colour":"#FFFFFFFF","tiledepth":1000000,"instanceid":10005180},{"pos":{"x":140,"y":40},"bg":"bg_ruinseasynam1","sourcepos":{"x":120,"y":40},"size":{"width":20,"height":20},"scale":{"x":1.0,"y":1.0},"colour":"#FFFFFFFF","tiledepth":1000000,"instanceid":10005181},{"pos":{"x":160,"y":40},"bg":"bg_ruinseasynam1","sourcepos":{"x":120,"y":40},"size":{"width":20,"height":20},"scale":{"x":1.0,"y":1.0},"colour":"#FFFFFFFF","tiledepth":1000000,"instanceid":10005182},{"pos":{"x":180,"y":40},"bg":"bg_ruinseasynam1","sourcepos":{"x":120,"y":40},"size":{"width":20,"height":20},"scale":{"x":1.0,"y":1.0},"colour":"#FFFFFFFF","tiledepth":1000000,"instanceid":10005183},{"pos":{"x":200,"y":40},"bg":"bg_ruinseasynam1","sourcepos":{"x":120,"y":40},"size":{"width":20,"height":20},"scale":{"x":1.0,"y":1.0},"colour":"#FFFFFFFF","tiledepth":1000000,"instanceid":10005184},{"pos":{"x":220,"y":40},"bg":"bg_ruinseasynam1","sourcepos":{"x":120,"y":40},"size":{"width":20,"height":20},"scale":{"x":1.0,"y":1.0},"colour":"#FFFFFFFF","tiledepth":1000000,"instanceid":10005185},{"pos":{"x":60,"y":200},"bg":"bg_ruinseasynam1","sourcepos":{"x":100,"y":80},"size":{"width":20,"height":20},"scale":{"x":1.0,"y":1.0},"colour":"#FFFFFFFF","tiledepth":1000000,"instanceid":10005186},{"pos":{"x":240,"y":200},"bg":"bg_ruinseasynam1","sourcepos":{"x":120,"y":80},"size":{"width":20,"height":20},"scale":{"x":1.0,"y":1.0},"colour":"#FFFFFFFF","tiledepth":1000000,"instanceid":10005187},{"pos":{"x":140,"y":180},"bg":"bg_ruinseasynam2","sourcepos":{"x":0,"y":40},"size":{"width":20,"height":20},"scale":{"x":1.0,"y":1.0},"colour":"#FFFFFFFF","tiledepth":1000000,"instanceid":10005188},{"pos":{"x":160,"y":180},"bg":"bg_ruinseasynam2","sourcepos":{"x":0,"y":40},"size":{"width":20,"height":20},"scale":{"x":1.0,"y":1.0},"colour":"#FFFFFFFF","tiledepth":1000000,"instanceid":10005189},{"pos":{"x":120,"y":200},"bg":"bg_ruinseasynam2","sourcepos":{"x":120,"y":0},"size":{"width":20,"height":20},"scale":{"x":1.0,"y":1.0},"colour":"#FFFFFFFF","tiledepth":1000000,"instanceid":10005190},{"pos":{"x":140,"y":200},"bg":"bg_ruinseasynam2","sourcepos":{"x":120,"y":0},"size":{"width":20,"height":20},"scale":{"x":1.0,"y":1.0},"colour":"#FFFFFFFF","tiledepth":1000000,"instanceid":10005191},{"pos":{"x":160,"y":200},"bg":"bg_ruinseasynam2","sourcepos":{"x":120,"y":0},"size":{"width":20,"height":20},"scale":{"x":1.0,"y":1.0},"colour":"#FFFFFFFF","tiledepth":1000000,"instanceid":10005192},{"pos":{"x":180,"y":200},"bg":"bg_ruinseasynam2","sourcepos":{"x":120,"y":0},"size":{"width":20,"height":20},"scale":{"x":1.0,"y":1.0},"colour":"#FFFFFFFF","tiledepth":1000000,"instanceid":10005193},{"pos":{"x":0,"y":140},"bg":"bg_ruinseasynam2","sourcepos":{"x":0,"y":20},"size":{"width":20,"height":20},"scale":{"x":1.0,"y":1.0},"colour":"#FFFFFFFF","tiledepth":1000000,"instanceid":10005194},{"pos":{"x":0,"y":120},"bg":"bg_ruinseasynam2","sourcepos":{"x":0,"y":20},"size":{"width":20,"height":20},"scale":{"x":1.0,"y":1.0},"colour":"#FFFFFFFF","tiledepth":1000000,"instanceid":10005195},{"pos":{"x":20,"y":120},"bg":"bg_ruinseasynam2","sourcepos":{"x":0,"y":20},"size":{"width":20,"height":20},"scale":{"x":1.0,"y":1.0},"colour":"#FFFFFFFF","tiledepth":1000000,"instanceid":10005196},{"pos":{"x":20,"y":140},"bg":"bg_ruinseasynam2","sourcepos":{"x":0,"y":20},"size":{"width":20,"height":20},"scale":{"x":1.0,"y":1.0},"colour":"#FFFFFFFF","tiledepth":1000000,"instanceid":10005197},{"pos":{"x":40,"y":140},"bg":"bg_ruinseasynam2","sourcepos":{"x":0,"y":20},"size":{"width":20,"height":20},"scale":{"x":1.0,"y":1.0},"colour":"#FFFFFFFF","tiledepth":1000000,"instanceid":10005198},{"pos":{"x":40,"y":120},"bg":"bg_ruinseasynam2","sourcepos":{"x":0,"y":20},"size":{"width":20,"height":20},"scale":{"x":1.0,"y":1.0},"colour":"#FFFFFFFF","tiledepth":1000000,"instanceid":10005199},{"pos":{"x":60,"y":120},"bg":"bg_ruinseasynam2","sourcepos":{"x":0,"y":20},"size":{"width":20,"height":20},"scale":{"x":1.0,"y":1.0},"colour":"#FFFFFFFF","tiledepth":1000000,"instanceid":10005200},{"pos":{"x":60,"y":140},"bg":"bg_ruinseasynam2","sourcepos":{"x":0,"y":20},"size":{"width":20,"height":20},"scale":{"x":1.0,"y":1.0},"colour":"#FFFFFFFF","tiledepth":1000000,"instanceid":10005201},{"pos":{"x":240,"y":120},"bg":"bg_ruinseasynam2","sourcepos":{"x":0,"y":20},"size":{"width":20,"height":20},"scale":{"x":1.0,"y":1.0},"colour":"#FFFFFFFF","tiledepth":1000000,"instanceid":10005202},{"pos":{"x":240,"y":140},"bg":"bg_ruinseasynam2","sourcepos":{"x":0,"y":20},"size":{"width":20,"height":20},"scale":{"x":1.0,"y":1.0},"colour":"#FFFFFFFF","tiledepth":1000000,"instanceid":10005203},{"pos":{"x":260,"y":140},"bg":"bg_ruinseasynam2","sourcepos":{"x":0,"y":20},"size":{"width":20,"height":20},"scale":{"x":1.0,"y":1.0},"colour":"#FFFFFFFF","tiledepth":1000000,"instanceid":10005204},{"pos":{"x":260,"y":120},"bg":"bg_ruinseasynam2","sourcepos":{"x":0,"y":20},"size":{"width":20,"height":20},"scale":{"x":1.0,"y":1.0},"colour":"#FFFFFFFF","tiledepth":1000000,"instanceid":10005205},{"pos":{"x":280,"y":120},"bg":"bg_ruinseasynam2","sourcepos":{"x":0,"y":20},"size":{"width":20,"height":20},"scale":{"x":1.0,"y":1.0},"colour":"#FFFFFFFF","tiledepth":1000000,"instanceid":10005206},{"pos":{"x":280,"y":140},"bg":"bg_ruinseasynam2","sourcepos":{"x":0,"y":20},"size":{"width":20,"height":20},"scale":{"x":1.0,"y":1.0},"colour":"#FFFFFFFF","tiledepth":1000000,"instanceid":10005207},{"pos":{"x":300,"y":140},"bg":"bg_ruinseasynam2","sourcepos":{"x":0,"y":20},"size":{"width":20,"height":20},"scale":{"x":1.0,"y":1.0},"colour":"#FFFFFFFF","tiledepth":1000000,"instanceid":10005208},{"pos":{"x":300,"y":120},"bg":"bg_ruinseasynam2","sourcepos":{"x":0,"y":20},"size":{"width":20,"height":20},"scale":{"x":1.0,"y":1.0},"colour":"#FFFFFFFF","tiledepth":1000000,"instanceid":10005209},{"pos":{"x":80,"y":140},"bg":"bg_ruinseasynam2","sourcepos":{"x":20,"y":80},"size":{"width":20,"height":20},"scale":{"x":1.0,"y":1.0},"colour":"#FFFFFFFF","tiledepth":1000000,"instanceid":10005210},{"pos":{"x":80,"y":120},"bg":"bg_ruinseasynam2","sourcepos":{"x":20,"y":60},"size":{"width":20,"height":20},"scale":{"x":1.0,"y":1.0},"colour":"#FFFFFFFF","tiledepth":1000000,"instanceid":10005211},{"pos":{"x":220,"y":120},"bg":"bg_ruinseasynam2","sourcepos":{"x":0,"y":60},"size":{"width":20,"height":20},"scale":{"x":1.0,"y":1.0},"colour":"#FFFFFFFF","tiledepth":1000000,"instanceid":10005212},{"pos":{"x":220,"y":140},"bg":"bg_ruinseasynam2","sourcepos":{"x":0,"y":80},"size":{"width":20,"height":20},"scale":{"x":1.0,"y":1.0},"colour":"#FFFFFFFF","tiledepth":1000000,"instanceid":10005213},{"pos":{"x":60,"y":160},"bg":"bg_ruinseasynam2","sourcepos":{"x":140,"y":0},"size":{"width":20,"height":20},"scale":{"x":1.0,"y":1.0},"colour":"#FFFFFFFF","tiledepth":1000000,"instanceid":10005214},{"pos":{"x":20,"y":160},"bg":"bg_ruinseasynam2","sourcepos":{"x":120,"y":0},"size":{"width":20,"height":20},"scale":{"x":1.0,"y":1.0},"colour":"#FFFFFFFF","tiledepth":1000000,"instanceid":10005215},{"pos":{"x":40,"y":160},"bg":"bg_ruinseasynam2","sourcepos":{"x":120,"y":0},"size":{"width":20,"height":20},"scale":{"x":1.0,"y":1.0},"colour":"#FFFFFFFF","tiledepth":1000000,"instanceid":10005216},{"pos":{"x":0,"y":160},"bg":"bg_ruinseasynam2","sourcepos":{"x":120,"y":0},"size":{"width":20,"height":20},"scale":{"x":1.0,"y":1.0},"colour":"#FFFFFFFF","tiledepth":1000000,"instanceid":10005217},{"pos":{"x":240,"y":160},"bg":"bg_ruinseasynam2","sourcepos":{"x":100,"y":0},"size":{"width":20,"height":20},"scale":{"x":1.0,"y":1.0},"colour":"#FFFFFFFF","tiledepth":1000000,"instanceid":10005218},{"pos":{"x":260,"y":160},"bg":"bg_ruinseasynam2","sourcepos":{"x":120,"y":0},"size":{"width":20,"height":20},"scale":{"x":1.0,"y":1.0},"colour":"#FFFFFFFF","tiledepth":1000000,"instanceid":10005219},{"pos":{"x":280,"y":160},"bg":"bg_ruinseasynam2","sourcepos":{"x":120,"y":0},"size":{"width":20,"height":20},"scale":{"x":1.0,"y":1.0},"colour":"#FFFFFFFF","tiledepth":1000000,"instanceid":10005220},{"pos":{"x":300,"y":160},"bg":"bg_ruinseasynam2","sourcepos":{"x":120,"y":0},"size":{"width":20,"height":20},"scale":{"x":1.0,"y":1.0},"colour":"#FFFFFFFF","tiledepth":1000000,"instanceid":10005221},{"pos":{"x":40,"y":80},"bg":"bg_ruinseasynam1","sourcepos":{"x":40,"y":0},"size":{"width":20,"height":20},"scale":{"x":1.0,"y":1.0},"colour":"#FFFFFFFF","tiledepth":1000000,"instanceid":10005222},{"pos":{"x":20,"y":80},"bg":"bg_ruinseasynam1","sourcepos":{"x":40,"y":0},"size":{"width":20,"height":20},"scale":{"x":1.0,"y":1.0},"colour":"#FFFFFFFF","tiledepth":1000000,"instanceid":10005223},{"pos":{"x":0,"y":80},"bg":"bg_ruinseasynam1","sourcepos":{"x":40,"y":0},"size":{"width":20,"height":20},"scale":{"x":1.0,"y":1.0},"colour":"#FFFFFFFF","tiledepth":1000000,"instanceid":10005224},{"pos":{"x":60,"y":80},"bg":"bg_ruinseasynam1","sourcepos":{"x":40,"y":0},"size":{"width":20,"height":20},"scale":{"x":1.0,"y":1.0},"colour":"#FFFFFFFF","tiledepth":1000000,"instanceid":10005225},{"pos":{"x":80,"y":80},"bg":"bg_ruinseasynam1","sourcepos":{"x":40,"y":0},"size":{"width":20,"height":20},"scale":{"x":1.0,"y":1.0},"colour":"#FFFFFFFF","tiledepth":1000000,"instanceid":10005226},{"pos":{"x":20,"y":60},"bg":"bg_ruinseasynam1","sourcepos":{"x":40,"y":0},"size":{"width":20,"height":20},"scale":{"x":1.0,"y":1.0},"colour":"#FFFFFFFF","tiledepth":1000000,"instanceid":10005227},{"pos":{"x":0,"y":60},"bg":"bg_ruinseasynam1","sourcepos":{"x":40,"y":0},"size":{"width":20,"height":20},"scale":{"x":1.0,"y":1.0},"colour":"#FFFFFFFF","tiledepth":1000000,"instanceid":10005228},{"pos":{"x":40,"y":60},"bg":"bg_ruinseasynam1","sourcepos":{"x":40,"y":0},"size":{"width":20,"height":20},"scale":{"x":1.0,"y":1.0},"colour":"#FFFFFFFF","tiledepth":1000000,"instanceid":10005229},{"pos":{"x":60,"y":60},"bg":"bg_ruinseasynam1","sourcepos":{"x":40,"y":0},"size":{"width":20,"height":20},"scale":{"x":1.0,"y":1.0},"colour":"#FFFFFFFF","tiledepth":1000000,"instanceid":10005230},{"pos":{"x":80,"y":60},"bg":"bg_ruinseasynam1","sourcepos":{"x":40,"y":0},"size":{"width":20,"height":20},"scale":{"x":1.0,"y":1.0},"colour":"#FFFFFFFF","tiledepth":1000000,"instanceid":10005231},{"pos":{"x":140,"y":60},"bg":"bg_ruinseasynam1","sourcepos":{"x":40,"y":0},"size":{"width":20,"height":20},"scale":{"x":1.0,"y":1.0},"colour":"#FFFFFFFF","tiledepth":1000000,"instanceid":10005232},{"pos":{"x":220,"y":60},"bg":"bg_ruinseasynam1","sourcepos":{"x":40,"y":0},"size":{"width":20,"height":20},"scale":{"x":1.0,"y":1.0},"colour":"#FFFFFFFF","tiledepth":1000000,"instanceid":10005233},{"pos":{"x":240,"y":60},"bg":"bg_ruinseasynam1","sourcepos":{"x":40,"y":0},"size":{"width":20,"height":20},"scale":{"x":1.0,"y":1.0},"colour":"#FFFFFFFF","tiledepth":1000000,"instanceid":10005234},{"pos":{"x":260,"y":60},"bg":"bg_ruinseasynam1","sourcepos":{"x":40,"y":0},"size":{"width":20,"height":20},"scale":{"x":1.0,"y":1.0},"colour":"#FFFFFFFF","tiledepth":1000000,"instanceid":10005235},{"pos":{"x":280,"y":60},"bg":"bg_ruinseasynam1","sourcepos":{"x":40,"y":0},"size":{"width":20,"height":20},"scale":{"x":1.0,"y":1.0},"colour":"#FFFFFFFF","tiledepth":1000000,"instanceid":10005236},{"pos":{"x":300,"y":60},"bg":"bg_ruinseasynam1","sourcepos":{"x":40,"y":0},"size":{"width":20,"height":20},"scale":{"x":1.0,"y":1.0},"colour":"#FFFFFFFF","tiledepth":1000000,"instanceid":10005237},{"pos":{"x":300,"y":80},"bg":"bg_ruinseasynam1","sourcepos":{"x":40,"y":0},"size":{"width":20,"height":20},"scale":{"x":1.0,"y":1.0},"colour":"#FFFFFFFF","tiledepth":1000000,"instanceid":10005238},{"pos":{"x":280,"y":80},"bg":"bg_ruinseasynam1","sourcepos":{"x":40,"y":0},"size":{"width":20,"height":20},"scale":{"x":1.0,"y":1.0},"colour":"#FFFFFFFF","tiledepth":1000000,"instanceid":10005239},{"pos":{"x":260,"y":80},"bg":"bg_ruinseasynam1","sourcepos":{"x":40,"y":0},"size":{"width":20,"height":20},"scale":{"x":1.0,"y":1.0},"colour":"#FFFFFFFF","tiledepth":1000000,"instanceid":10005240},{"pos":{"x":240,"y":80},"bg":"bg_ruinseasynam1","sourcepos":{"x":40,"y":0},"size":{"width":20,"height":20},"scale":{"x":1.0,"y":1.0},"colour":"#FFFFFFFF","tiledepth":1000000,"instanceid":10005241},{"pos":{"x":220,"y":80},"bg":"bg_ruinseasynam1","sourcepos":{"x":40,"y":0},"size":{"width":20,"height":20},"scale":{"x":1.0,"y":1.0},"colour":"#FFFFFFFF","tiledepth":1000000,"instanceid":10005242},{"pos":{"x":40,"y":40},"bg":"bg_ruinseasynam1","sourcepos":{"x":120,"y":40},"size":{"width":20,"height":20},"scale":{"x":1.0,"y":1.0},"colour":"#FFFFFFFF","tiledepth":1000000,"instanceid":10005243},{"pos":{"x":80,"y":40},"bg":"bg_ruinseasynam1","sourcepos":{"x":120,"y":40},"size":{"width":20,"height":20},"scale":{"x":1.0,"y":1.0},"colour":"#FFFFFFFF","tiledepth":1000000,"instanceid":10005244},{"pos":{"x":60,"y":40},"bg":"bg_ruinseasynam1","sourcepos":{"x":120,"y":40},"size":{"width":20,"height":20},"scale":{"x":1.0,"y":1.0},"colour":"#FFFFFFFF","tiledepth":1000000,"instanceid":10005245},{"pos":{"x":20,"y":40},"bg":"bg_ruinseasynam1","sourcepos":{"x":120,"y":40},"size":{"width":20,"height":20},"scale":{"x":1.0,"y":1.0},"colour":"#FFFFFFFF","tiledepth":1000000,"instanceid":10005246},{"pos":{"x":0,"y":40},"bg":"bg_ruinseasynam1","sourcepos":{"x":120,"y":40},"size":{"width":20,"height":20},"scale":{"x":1.0,"y":1.0},"colour":"#FFFFFFFF","tiledepth":1000000,"instanceid":10005247},{"pos":{"x":240,"y":40},"bg":"bg_ruinseasynam1","sourcepos":{"x":120,"y":40},"size":{"width":20,"height":20},"scale":{"x":1.0,"y":1.0},"colour":"#FFFFFFFF","tiledepth":1000000,"instanceid":10005248},{"pos":{"x":260,"y":40},"bg":"bg_ruinseasynam1","sourcepos":{"x":120,"y":40},"size":{"width":20,"height":20},"scale":{"x":1.0,"y":1.0},"colour":"#FFFFFFFF","tiledepth":1000000,"instanceid":10005249},{"pos":{"x":280,"y":40},"bg":"bg_ruinseasynam1","sourcepos":{"x":120,"y":40},"size":{"width":20,"height":20},"scale":{"x":1.0,"y":1.0},"colour":"#FFFFFFFF","tiledepth":1000000,"instanceid":10005250},{"pos":{"x":300,"y":40},"bg":"bg_ruinseasynam1","sourcepos":{"x":120,"y":40},"size":{"width":20,"height":20},"scale":{"x":1.0,"y":1.0},"colour":"#FFFFFFFF","tiledepth":1000000,"instanceid":10005251},{"pos":{"x":0,"y":100},"bg":"bg_ruinseasynam3","sourcepos":{"x":20,"y":160},"size":{"width":20,"height":20},"scale":{"x":1.0,"y":1.0},"colour":"#FFFFFFFF","tiledepth":1000000,"instanceid":10005252},{"pos":{"x":40,"y":100},"bg":"bg_ruinseasynam3","sourcepos":{"x":20,"y":160},"size":{"width":20,"height":20},"scale":{"x":1.0,"y":1.0},"colour":"#FFFFFFFF","tiledepth":1000000,"instanceid":10005253},{"pos":{"x":20,"y":100},"bg":"bg_ruinseasynam3","sourcepos":{"x":20,"y":160},"size":{"width":20,"height":20},"scale":{"x":1.0,"y":1.0},"colour":"#FFFFFFFF","tiledepth":1000000,"instanceid":10005254},{"pos":{"x":60,"y":100},"bg":"bg_ruinseasynam3","sourcepos":{"x":20,"y":160},"size":{"width":20,"height":20},"scale":{"x":1.0,"y":1.0},"colour":"#FFFFFFFF","tiledepth":1000000,"instanceid":10005255},{"pos":{"x":80,"y":100},"bg":"bg_ruinseasynam3","sourcepos":{"x":20,"y":160},"size":{"width":20,"height":20},"scale":{"x":1.0,"y":1.0},"colour":"#FFFFFFFF","tiledepth":1000000,"instanceid":10005256},{"pos":{"x":100,"y":100},"bg":"bg_ruinseasynam3","sourcepos":{"x":20,"y":160},"size":{"width":20,"height":20},"scale":{"x":1.0,"y":1.0},"colour":"#FFFFFFFF","tiledepth":1000000,"instanceid":10005257},{"pos":{"x":120,"y":100},"bg":"bg_ruinseasynam3","sourcepos":{"x":20,"y":160},"size":{"width":20,"height":20},"scale":{"x":1.0,"y":1.0},"colour":"#FFFFFFFF","tiledepth":1000000,"instanceid":10005258},{"pos":{"x":140,"y":100},"bg":"bg_ruinseasynam3","sourcepos":{"x":20,"y":160},"size":{"width":20,"height":20},"scale":{"x":1.0,"y":1.0},"colour":"#FFFFFFFF","tiledepth":1000000,"instanceid":10005259},{"pos":{"x":160,"y":100},"bg":"bg_ruinseasynam3","sourcepos":{"x":20,"y":160},"size":{"width":20,"height":20},"scale":{"x":1.0,"y":1.0},"colour":"#FFFFFFFF","tiledepth":1000000,"instanceid":10005260},{"pos":{"x":180,"y":100},"bg":"bg_ruinseasynam3","sourcepos":{"x":20,"y":160},"size":{"width":20,"height":20},"scale":{"x":1.0,"y":1.0},"colour":"#FFFFFFFF","tiledepth":1000000,"instanceid":10005261},{"pos":{"x":200,"y":100},"bg":"bg_ruinseasynam3","sourcepos":{"x":20,"y":160},"size":{"width":20,"height":20},"scale":{"x":1.0,"y":1.0},"colour":"#FFFFFFFF","tiledepth":1000000,"instanceid":10005262},{"pos":{"x":220,"y":100},"bg":"bg_ruinseasynam3","sourcepos":{"x":20,"y":160},"size":{"width":20,"height":20},"scale":{"x":1.0,"y":1.0},"colour":"#FFFFFFFF","tiledepth":1000000,"instanceid":10005263},{"pos":{"x":240,"y":100},"bg":"bg_ruinseasynam3","sourcepos":{"x":20,"y":160},"size":{"width":20,"height":20},"scale":{"x":1.0,"y":1.0},"colour":"#FFFFFFFF","tiledepth":1000000,"instanceid":10005264},{"pos":{"x":260,"y":100},"bg":"bg_ruinseasynam3","sourcepos":{"x":20,"y":160},"size":{"width":20,"height":20},"scale":{"x":1.0,"y":1.0},"colour":"#FFFFFFFF","tiledepth":1000000,"instanceid":10005265},{"pos":{"x":280,"y":100},"bg":"bg_ruinseasynam3","sourcepos":{"x":20,"y":160},"size":{"width":20,"height":20},"scale":{"x":1.0,"y":1.0},"colour":"#FFFFFFFF","tiledepth":1000000,"instanceid":10005266},{"pos":{"x":300,"y":100},"bg":"bg_ruinseasynam3","sourcepos":{"x":20,"y":160},"size":{"width":20,"height":20},"scale":{"x":1.0,"y":1.0},"colour":"#FFFFFFFF","tiledepth":1000000,"instanceid":10005267}]}