{"size":{"width":21,"height":10},"bounding":{"top":0,"left":0,"bottom":9,"right":20},"bboxmode":0,"sepmasks":false,"origin":{"x":0,"y":0},"textures":[3944],"colmasks":[{"w":21,"h":10,"data":[[true,true,true,true,true,true,true,true,true,true,true,true,true,true,true,true,false,false,false,true,true],[true,true,false,false,true,false,false,false,false,false,false,false,false,false,false,false,false,false,false,false,false],[true,false,false,false,false,false,false,false,false,false,false,false,false,false,false,false,false,false,false,false,false],[false,false,true,true,true,false,true,false,true,false,false,false,false,false,true,true,false,true,true,true,false],[true,false,false,false,false,false,false,false,false,false,false,false,false,false,false,false,false,false,false,false,false],[false,false,false,false,true,true,true,true,true,true,true,true,true,true,true,true,true,true,true,true,true],[false,false,false,false,true,true,true,true,true,true,true,true,true,true,true,true,true,true,true,true,true],[true,false,true,false,true,false,false,false,false,false,false,false,false,false,false,false,false,false,false,false,false],[false,false,false,false,false,false,false,false,false,false,false,false,false,false,false,false,false,false,false,false,false],[true,false,false,false,false,false,false,false,false,false,false,false,false,false,false,false,false,false,false,false,false]]}]}